{"set":"grn","name":"Guilds of Ravnica","updated":"2026-01-24T00:20:36.112Z","play":[{"id":"b8ebe3cf-7143-453a-b0ef-2f5bdaac3185","name":"Steam Vents","set":"grn","collector_number":"257","rarity":"rare","booster":true,"image":"https://cards.scryfall.io/normal/front/b/8/b8ebe3cf-7143-453a-b0ef-2f5bdaac3185.jpg?1572894204","uri":"https://scryfall.com/card/grn/257/steam-vents?utm_source=api","finishes":[{"type":"nonfoil","price":15.89},{"type":"foil","price":19.53}],"showcase":false,"extendedart":false,"inverted":false,"borderless":false,"fullart":false,"etched":false,"promo":false,"promo_types":[]},{"id":"2b9b0195-beda-403e-bc27-7ae3be9f318c","name":"Temple Garden","set":"grn","collector_number":"258","rarity":"rare","booster":true,"image":"https://cards.scryfall.io/normal/front/2/b/2b9b0195-beda-403e-bc27-7ae3be9f318c.jpg?1572894210","uri":"https://scryfall.com/card/grn/258/temple-garden?utm_source=api","finishes":[{"type":"nonfoil","price":12.02},{"type":"foil","price":14.31}],"showcase":false,"extendedart":false,"inverted":false,"borderless":false,"fullart":false,"etched":false,"promo":false,"promo_types":[]},{"id":"eff1f52c-5c43-4260-aaa0-6920846a191c","name":"Overgrown Tomb","set":"grn","collector_number":"253","rarity":"rare","booster":true,"image":"https://cards.scryfall.io/normal/front/e/f/eff1f52c-5c43-4260-aaa0-6920846a191c.jpg?1572894177","uri":"https://scryfall.com/card/grn/253/overgrown-tomb?utm_source=api","finishes":[{"type":"nonfoil","price":11.53},{"type":"foil","price":14.14}],"showcase":false,"extendedart":false,"inverted":false,"borderless":false,"fullart":false,"etched":false,"promo":false,"promo_types":[]},{"id":"7d4595f2-9297-40dc-b2dd-7144bbb401f7","name":"Watery Grave","set":"grn","collector_number":"259","rarity":"rare","booster":true,"image":"https://cards.scryfall.io/normal/front/7/d/7d4595f2-9297-40dc-b2dd-7144bbb401f7.jpg?1572894217","uri":"https://scryfall.com/card/grn/259/watery-grave?utm_source=api","finishes":[{"type":"nonfoil","price":8.62},{"type":"foil","price":14.8}],"showcase":false,"extendedart":false,"inverted":false,"borderless":false,"fullart":false,"etched":false,"promo":false,"promo_types":[]},{"id":"a5cf45aa-ed34-4add-a2ec-fc11f8c15ffa","name":"Mnemonic Betrayal","set":"grn","collector_number":"189","rarity":"mythic","booster":true,"image":"https://cards.scryfall.io/normal/front/a/5/a5cf45aa-ed34-4add-a2ec-fc11f8c15ffa.jpg?1572893747","uri":"https://scryfall.com/card/grn/189/mnemonic-betrayal?utm_source=api","finishes":[{"type":"nonfoil","price":8.6},{"type":"foil","price":61.08}],"showcase":false,"extendedart":false,"inverted":false,"borderless":false,"fullart":false,"etched":false,"promo":false,"promo_types":[]},{"id":"b7b598d0-535d-477d-a33d-d6a10ff5439a","name":"Sacred Foundry","set":"grn","collector_number":"254","rarity":"rare","booster":true,"image":"https://cards.scryfall.io/normal/front/b/7/b7b598d0-535d-477d-a33d-d6a10ff5439a.jpg?1572894184","uri":"https://scryfall.com/card/grn/254/sacred-foundry?utm_source=api","finishes":[{"type":"nonfoil","price":8.35},{"type":"foil","price":14.52}],"showcase":false,"extendedart":false,"inverted":false,"borderless":false,"fullart":false,"etched":false,"promo":false,"promo_types":[]},{"id":"0782e090-209c-428f-966a-17f3ceab2903","name":"Underrealm Lich","set":"grn","collector_number":"211","rarity":"mythic","booster":true,"image":"https://cards.scryfall.io/normal/front/0/7/0782e090-209c-428f-966a-17f3ceab2903.jpg?1572893891","uri":"https://scryfall.com/card/grn/211/underrealm-lich?utm_source=api","finishes":[{"type":"nonfoil","price":4.87},{"type":"foil","price":11.62}],"showcase":false,"extendedart":false,"inverted":false,"borderless":false,"fullart":false,"etched":false,"promo":false,"promo_types":[]},{"id":"9da6f595-41b2-4e52-b15a-6ad18e4232c7","name":"Beast Whisperer","set":"grn","collector_number":"123","rarity":"rare","booster":true,"image":"https://cards.scryfall.io/normal/front/9/d/9da6f595-41b2-4e52-b15a-6ad18e4232c7.jpg?1572893306","uri":"https://scryfall.com/card/grn/123/beast-whisperer?utm_source=api","finishes":[{"type":"nonfoil","price":3.72},{"type":"foil","price":3.41}],"showcase":false,"extendedart":false,"inverted":false,"borderless":false,"fullart":false,"etched":false,"promo":false,"promo_types":[]},{"id":"906b6e99-128f-4c11-8daf-16099d35b0d4","name":"Assassin's Trophy","set":"grn","collector_number":"152","rarity":"rare","booster":true,"image":"https://cards.scryfall.io/normal/front/9/0/906b6e99-128f-4c11-8daf-16099d35b0d4.jpg?1572893498","uri":"https://scryfall.com/card/grn/152/assassins-trophy?utm_source=api","finishes":[{"type":"nonfoil","price":3.44},{"type":"foil","price":4.99}],"showcase":false,"extendedart":false,"inverted":false,"borderless":false,"fullart":false,"etched":false,"promo":false,"promo_types":[]},{"id":"6f3d2dc5-7b9d-4af6-9f3b-4de90fbf63c9","name":"Niv-Mizzet, Parun","set":"grn","collector_number":"192","rarity":"rare","booster":true,"image":"https://cards.scryfall.io/normal/front/6/f/6f3d2dc5-7b9d-4af6-9f3b-4de90fbf63c9.jpg?1572893767","uri":"https://scryfall.com/card/grn/192/niv-mizzet-parun?utm_source=api","finishes":[{"type":"nonfoil","price":3.37},{"type":"foil","price":7.07}],"showcase":false,"extendedart":false,"inverted":false,"borderless":false,"fullart":false,"etched":false,"promo":false,"promo_types":[]},{"id":"0a11ee0d-ff8d-4648-8b4e-29440c135c30","name":"Doom Whisperer","set":"grn","collector_number":"69","rarity":"mythic","booster":true,"image":"https://cards.scryfall.io/normal/front/0/a/0a11ee0d-ff8d-4648-8b4e-29440c135c30.jpg?1572892944","uri":"https://scryfall.com/card/grn/69/doom-whisperer?utm_source=api","finishes":[{"type":"nonfoil","price":3.06},{"type":"foil","price":11.55}],"showcase":false,"extendedart":false,"inverted":false,"borderless":false,"fullart":false,"etched":false,"promo":false,"promo_types":[]},{"id":"a36d3ea7-0f18-4865-b47b-755673db065e","name":"Vraska, Golgari Queen","set":"grn","collector_number":"213","rarity":"mythic","booster":true,"image":"https://cards.scryfall.io/normal/front/a/3/a36d3ea7-0f18-4865-b47b-755673db065e.jpg?1572893904","uri":"https://scryfall.com/card/grn/213/vraska-golgari-queen?utm_source=api","finishes":[{"type":"nonfoil","price":2.8},{"type":"foil","price":6.44}],"showcase":false,"extendedart":false,"inverted":false,"borderless":false,"fullart":false,"etched":false,"promo":false,"promo_types":[]},{"id":"ea123356-3055-4e42-b816-ac3c4e9087d1","name":"Chromatic Lantern","set":"grn","collector_number":"233","rarity":"rare","booster":true,"image":"https://cards.scryfall.io/normal/front/e/a/ea123356-3055-4e42-b816-ac3c4e9087d1.jpg?1572894045","uri":"https://scryfall.com/card/grn/233/chromatic-lantern?utm_source=api","finishes":[{"type":"nonfoil","price":2.57},{"type":"foil","price":4.1}],"showcase":false,"extendedart":false,"inverted":false,"borderless":false,"fullart":false,"etched":false,"promo":false,"promo_types":[]},{"id":"da3789d4-3621-44a1-bb72-8e3bbac8bf72","name":"Divine Visitation","set":"grn","collector_number":"10","rarity":"mythic","booster":true,"image":"https://cards.scryfall.io/normal/front/d/a/da3789d4-3621-44a1-bb72-8e3bbac8bf72.jpg?1572892535","uri":"https://scryfall.com/card/grn/10/divine-visitation?utm_source=api","finishes":[{"type":"nonfoil","price":2.1},{"type":"foil","price":5.23}],"showcase":false,"extendedart":false,"inverted":false,"borderless":false,"fullart":false,"etched":false,"promo":false,"promo_types":[]},{"id":"85edf6f9-b863-41e2-bb51-857ea2798090","name":"Chance for Glory","set":"grn","collector_number":"159","rarity":"mythic","booster":true,"image":"https://cards.scryfall.io/normal/front/8/5/85edf6f9-b863-41e2-bb51-857ea2798090.jpg?1572893545","uri":"https://scryfall.com/card/grn/159/chance-for-glory?utm_source=api","finishes":[{"type":"nonfoil","price":1.51},{"type":"foil","price":19.54}],"showcase":false,"extendedart":false,"inverted":false,"borderless":false,"fullart":false,"etched":false,"promo":false,"promo_types":[]},{"id":"270a0863-7d07-43f0-925d-a8ce0383a1cb","name":"Thousand-Year Storm","set":"grn","collector_number":"207","rarity":"mythic","booster":true,"image":"https://cards.scryfall.io/normal/front/2/7/270a0863-7d07-43f0-925d-a8ce0383a1cb.jpg?1572893865","uri":"https://scryfall.com/card/grn/207/thousand-year-storm?utm_source=api","finishes":[{"type":"nonfoil","price":1.09},{"type":"foil","price":1.67}],"showcase":false,"extendedart":false,"inverted":false,"borderless":false,"fullart":false,"etched":false,"promo":false,"promo_types":[]},{"id":"d8c9c111-fbc7-44e1-94bd-1ca164370623","name":"Runaway Steam-Kin","set":"grn","collector_number":"115","rarity":"rare","booster":true,"image":"https://cards.scryfall.io/normal/front/d/8/d8c9c111-fbc7-44e1-94bd-1ca164370623.jpg?1572893254","uri":"https://scryfall.com/card/grn/115/runaway-steam-kin?utm_source=api","finishes":[{"type":"nonfoil","price":0.98},{"type":"foil","price":3.95}],"showcase":false,"extendedart":false,"inverted":false,"borderless":false,"fullart":false,"etched":false,"promo":false,"promo_types":[]},{"id":"2cc2b646-0181-4f0a-a141-00ca56069a06","name":"March of the Multitudes","set":"grn","collector_number":"188","rarity":"mythic","booster":true,"image":"https://cards.scryfall.io/normal/front/2/c/2cc2b646-0181-4f0a-a141-00ca56069a06.jpg?1572893740","uri":"https://scryfall.com/card/grn/188/march-of-the-multitudes?utm_source=api","finishes":[{"type":"nonfoil","price":0.88},{"type":"foil","price":5.19}],"showcase":false,"extendedart":false,"inverted":false,"borderless":false,"fullart":false,"etched":false,"promo":false,"promo_types":[]},{"id":"7096c9a6-2e73-41f8-b20a-b29a9f0b760c","name":"Electrostatic Field","set":"grn","collector_number":"97","rarity":"uncommon","booster":true,"image":"https://cards.scryfall.io/normal/front/7/0/7096c9a6-2e73-41f8-b20a-b29a9f0b760c.jpg?1712534108","uri":"https://scryfall.com/card/grn/97/electrostatic-field?utm_source=api","finishes":[{"type":"nonfoil","price":0.86},{"type":"foil","price":6.31}],"showcase":false,"extendedart":false,"inverted":false,"borderless":false,"fullart":false,"etched":false,"promo":false,"promo_types":[]},{"id":"a8e9f4d2-bba5-4061-8ae7-a68b912f2c11","name":"Aurelia, Exemplar of Justice","set":"grn","collector_number":"153","rarity":"mythic","booster":true,"image":"https://cards.scryfall.io/normal/front/a/8/a8e9f4d2-bba5-4061-8ae7-a68b912f2c11.jpg?1572893504","uri":"https://scryfall.com/card/grn/153/aurelia-exemplar-of-justice?utm_source=api","finishes":[{"type":"nonfoil","price":0.77},{"type":"foil","price":2.11}],"showcase":false,"extendedart":false,"inverted":false,"borderless":false,"fullart":false,"etched":false,"promo":false,"promo_types":[]},{"id":"fa36b142-e67e-49da-9080-c5994e275266","name":"Etrata, the Silencer","set":"grn","collector_number":"170","rarity":"rare","booster":true,"image":"https://cards.scryfall.io/normal/front/f/a/fa36b142-e67e-49da-9080-c5994e275266.jpg?1572893618","uri":"https://scryfall.com/card/grn/170/etrata-the-silencer?utm_source=api","finishes":[{"type":"nonfoil","price":0.66},{"type":"foil","price":3.44}],"showcase":false,"extendedart":false,"inverted":false,"borderless":false,"fullart":false,"etched":false,"promo":false,"promo_types":[]},{"id":"5e84cb9c-9876-47a4-aea4-78574321bc36","name":"Legion Warboss","set":"grn","collector_number":"109","rarity":"rare","booster":true,"image":"https://cards.scryfall.io/normal/front/5/e/5e84cb9c-9876-47a4-aea4-78574321bc36.jpg?1572893214","uri":"https://scryfall.com/card/grn/109/legion-warboss?utm_source=api","finishes":[{"type":"nonfoil","price":0.59},{"type":"foil","price":0.97}],"showcase":false,"extendedart":false,"inverted":false,"borderless":false,"fullart":false,"etched":false,"promo":false,"promo_types":[]},{"id":"bfc98428-7a0f-445f-9d48-eeb76c3e10d6","name":"Drowned Secrets","set":"grn","collector_number":"39","rarity":"rare","booster":true,"image":"https://cards.scryfall.io/normal/front/b/f/bfc98428-7a0f-445f-9d48-eeb76c3e10d6.jpg?1687687913","uri":"https://scryfall.com/card/grn/39/drowned-secrets?utm_source=api","finishes":[{"type":"nonfoil","price":0.57},{"type":"foil","price":1.16}],"showcase":false,"extendedart":false,"inverted":false,"borderless":false,"fullart":false,"etched":false,"promo":false,"promo_types":[]},{"id":"26f7cf38-78cc-4139-9f2a-4dd0be7d9da8","name":"Mausoleum Secrets","set":"grn","collector_number":"75","rarity":"rare","booster":true,"image":"https://cards.scryfall.io/normal/front/2/6/26f7cf38-78cc-4139-9f2a-4dd0be7d9da8.jpg?1572892984","uri":"https://scryfall.com/card/grn/75/mausoleum-secrets?utm_source=api","finishes":[{"type":"nonfoil","price":0.55},{"type":"foil","price":2.14}],"showcase":false,"extendedart":false,"inverted":false,"borderless":false,"fullart":false,"etched":false,"promo":false,"promo_types":[]},{"id":"c52066b3-84dc-4198-8090-3336e7df8b5d","name":"Ral, Izzet Viceroy","set":"grn","collector_number":"195","rarity":"mythic","booster":true,"image":"https://cards.scryfall.io/normal/front/c/5/c52066b3-84dc-4198-8090-3336e7df8b5d.jpg?1572893786","uri":"https://scryfall.com/card/grn/195/ral-izzet-viceroy?utm_source=api","finishes":[{"type":"nonfoil","price":0.52},{"type":"foil","price":1.68}],"showcase":false,"extendedart":false,"inverted":false,"borderless":false,"fullart":false,"etched":false,"promo":false,"promo_types":[]}],"collector":[{"id":"b8ebe3cf-7143-453a-b0ef-2f5bdaac3185","name":"Steam Vents","set":"grn","collector_number":"257","rarity":"rare","booster":true,"image":"https://cards.scryfall.io/normal/front/b/8/b8ebe3cf-7143-453a-b0ef-2f5bdaac3185.jpg?1572894204","uri":"https://scryfall.com/card/grn/257/steam-vents?utm_source=api","finishes":[{"type":"nonfoil","price":15.89},{"type":"foil","price":19.53}],"showcase":false,"extendedart":false,"inverted":false,"borderless":false,"fullart":false,"etched":false,"promo":false,"promo_types":[]},{"id":"2b9b0195-beda-403e-bc27-7ae3be9f318c","name":"Temple Garden","set":"grn","collector_number":"258","rarity":"rare","booster":true,"image":"https://cards.scryfall.io/normal/front/2/b/2b9b0195-beda-403e-bc27-7ae3be9f318c.jpg?1572894210","uri":"https://scryfall.com/card/grn/258/temple-garden?utm_source=api","finishes":[{"type":"nonfoil","price":12.02},{"type":"foil","price":14.31}],"showcase":false,"extendedart":false,"inverted":false,"borderless":false,"fullart":false,"etched":false,"promo":false,"promo_types":[]},{"id":"eff1f52c-5c43-4260-aaa0-6920846a191c","name":"Overgrown Tomb","set":"grn","collector_number":"253","rarity":"rare","booster":true,"image":"https://cards.scryfall.io/normal/front/e/f/eff1f52c-5c43-4260-aaa0-6920846a191c.jpg?1572894177","uri":"https://scryfall.com/card/grn/253/overgrown-tomb?utm_source=api","finishes":[{"type":"nonfoil","price":11.53},{"type":"foil","price":14.14}],"showcase":false,"extendedart":false,"inverted":false,"borderless":false,"fullart":false,"etched":false,"promo":false,"promo_types":[]},{"id":"7d4595f2-9297-40dc-b2dd-7144bbb401f7","name":"Watery Grave","set":"grn","collector_number":"259","rarity":"rare","booster":true,"image":"https://cards.scryfall.io/normal/front/7/d/7d4595f2-9297-40dc-b2dd-7144bbb401f7.jpg?1572894217","uri":"https://scryfall.com/card/grn/259/watery-grave?utm_source=api","finishes":[{"type":"nonfoil","price":8.62},{"type":"foil","price":14.8}],"showcase":false,"extendedart":false,"inverted":false,"borderless":false,"fullart":false,"etched":false,"promo":false,"promo_types":[]},{"id":"a5cf45aa-ed34-4add-a2ec-fc11f8c15ffa","name":"Mnemonic Betrayal","set":"grn","collector_number":"189","rarity":"mythic","booster":true,"image":"https://cards.scryfall.io/normal/front/a/5/a5cf45aa-ed34-4add-a2ec-fc11f8c15ffa.jpg?1572893747","uri":"https://scryfall.com/card/grn/189/mnemonic-betrayal?utm_source=api","finishes":[{"type":"nonfoil","price":8.6},{"type":"foil","price":61.08}],"showcase":false,"extendedart":false,"inverted":false,"borderless":false,"fullart":false,"etched":false,"promo":false,"promo_types":[]},{"id":"b7b598d0-535d-477d-a33d-d6a10ff5439a","name":"Sacred Foundry","set":"grn","collector_number":"254","rarity":"rare","booster":true,"image":"https://cards.scryfall.io/normal/front/b/7/b7b598d0-535d-477d-a33d-d6a10ff5439a.jpg?1572894184","uri":"https://scryfall.com/card/grn/254/sacred-foundry?utm_source=api","finishes":[{"type":"nonfoil","price":8.35},{"type":"foil","price":14.52}],"showcase":false,"extendedart":false,"inverted":false,"borderless":false,"fullart":false,"etched":false,"promo":false,"promo_types":[]},{"id":"0782e090-209c-428f-966a-17f3ceab2903","name":"Underrealm Lich","set":"grn","collector_number":"211","rarity":"mythic","booster":true,"image":"https://cards.scryfall.io/normal/front/0/7/0782e090-209c-428f-966a-17f3ceab2903.jpg?1572893891","uri":"https://scryfall.com/card/grn/211/underrealm-lich?utm_source=api","finishes":[{"type":"nonfoil","price":4.87},{"type":"foil","price":11.62}],"showcase":false,"extendedart":false,"inverted":false,"borderless":false,"fullart":false,"etched":false,"promo":false,"promo_types":[]},{"id":"9da6f595-41b2-4e52-b15a-6ad18e4232c7","name":"Beast Whisperer","set":"grn","collector_number":"123","rarity":"rare","booster":true,"image":"https://cards.scryfall.io/normal/front/9/d/9da6f595-41b2-4e52-b15a-6ad18e4232c7.jpg?1572893306","uri":"https://scryfall.com/card/grn/123/beast-whisperer?utm_source=api","finishes":[{"type":"nonfoil","price":3.72},{"type":"foil","price":3.41}],"showcase":false,"extendedart":false,"inverted":false,"borderless":false,"fullart":false,"etched":false,"promo":false,"promo_types":[]},{"id":"906b6e99-128f-4c11-8daf-16099d35b0d4","name":"Assassin's Trophy","set":"grn","collector_number":"152","rarity":"rare","booster":true,"image":"https://cards.scryfall.io/normal/front/9/0/906b6e99-128f-4c11-8daf-16099d35b0d4.jpg?1572893498","uri":"https://scryfall.com/card/grn/152/assassins-trophy?utm_source=api","finishes":[{"type":"nonfoil","price":3.44},{"type":"foil","price":4.99}],"showcase":false,"extendedart":false,"inverted":false,"borderless":false,"fullart":false,"etched":false,"promo":false,"promo_types":[]},{"id":"6f3d2dc5-7b9d-4af6-9f3b-4de90fbf63c9","name":"Niv-Mizzet, Parun","set":"grn","collector_number":"192","rarity":"rare","booster":true,"image":"https://cards.scryfall.io/normal/front/6/f/6f3d2dc5-7b9d-4af6-9f3b-4de90fbf63c9.jpg?1572893767","uri":"https://scryfall.com/card/grn/192/niv-mizzet-parun?utm_source=api","finishes":[{"type":"nonfoil","price":3.37},{"type":"foil","price":7.07}],"showcase":false,"extendedart":false,"inverted":false,"borderless":false,"fullart":false,"etched":false,"promo":false,"promo_types":[]},{"id":"0a11ee0d-ff8d-4648-8b4e-29440c135c30","name":"Doom Whisperer","set":"grn","collector_number":"69","rarity":"mythic","booster":true,"image":"https://cards.scryfall.io/normal/front/0/a/0a11ee0d-ff8d-4648-8b4e-29440c135c30.jpg?1572892944","uri":"https://scryfall.com/card/grn/69/doom-whisperer?utm_source=api","finishes":[{"type":"nonfoil","price":3.06},{"type":"foil","price":11.55}],"showcase":false,"extendedart":false,"inverted":false,"borderless":false,"fullart":false,"etched":false,"promo":false,"promo_types":[]},{"id":"a36d3ea7-0f18-4865-b47b-755673db065e","name":"Vraska, Golgari Queen","set":"grn","collector_number":"213","rarity":"mythic","booster":true,"image":"https://cards.scryfall.io/normal/front/a/3/a36d3ea7-0f18-4865-b47b-755673db065e.jpg?1572893904","uri":"https://scryfall.com/card/grn/213/vraska-golgari-queen?utm_source=api","finishes":[{"type":"nonfoil","price":2.8},{"type":"foil","price":6.44}],"showcase":false,"extendedart":false,"inverted":false,"borderless":false,"fullart":false,"etched":false,"promo":false,"promo_types":[]},{"id":"ea123356-3055-4e42-b816-ac3c4e9087d1","name":"Chromatic Lantern","set":"grn","collector_number":"233","rarity":"rare","booster":true,"image":"https://cards.scryfall.io/normal/front/e/a/ea123356-3055-4e42-b816-ac3c4e9087d1.jpg?1572894045","uri":"https://scryfall.com/card/grn/233/chromatic-lantern?utm_source=api","finishes":[{"type":"nonfoil","price":2.57},{"type":"foil","price":4.1}],"showcase":false,"extendedart":false,"inverted":false,"borderless":false,"fullart":false,"etched":false,"promo":false,"promo_types":[]},{"id":"da3789d4-3621-44a1-bb72-8e3bbac8bf72","name":"Divine Visitation","set":"grn","collector_number":"10","rarity":"mythic","booster":true,"image":"https://cards.scryfall.io/normal/front/d/a/da3789d4-3621-44a1-bb72-8e3bbac8bf72.jpg?1572892535","uri":"https://scryfall.com/card/grn/10/divine-visitation?utm_source=api","finishes":[{"type":"nonfoil","price":2.1},{"type":"foil","price":5.23}],"showcase":false,"extendedart":false,"inverted":false,"borderless":false,"fullart":false,"etched":false,"promo":false,"promo_types":[]},{"id":"85edf6f9-b863-41e2-bb51-857ea2798090","name":"Chance for Glory","set":"grn","collector_number":"159","rarity":"mythic","booster":true,"image":"https://cards.scryfall.io/normal/front/8/5/85edf6f9-b863-41e2-bb51-857ea2798090.jpg?1572893545","uri":"https://scryfall.com/card/grn/159/chance-for-glory?utm_source=api","finishes":[{"type":"nonfoil","price":1.51},{"type":"foil","price":19.54}],"showcase":false,"extendedart":false,"inverted":false,"borderless":false,"fullart":false,"etched":false,"promo":false,"promo_types":[]},{"id":"270a0863-7d07-43f0-925d-a8ce0383a1cb","name":"Thousand-Year Storm","set":"grn","collector_number":"207","rarity":"mythic","booster":true,"image":"https://cards.scryfall.io/normal/front/2/7/270a0863-7d07-43f0-925d-a8ce0383a1cb.jpg?1572893865","uri":"https://scryfall.com/card/grn/207/thousand-year-storm?utm_source=api","finishes":[{"type":"nonfoil","price":1.09},{"type":"foil","price":1.67}],"showcase":false,"extendedart":false,"inverted":false,"borderless":false,"fullart":false,"etched":false,"promo":false,"promo_types":[]},{"id":"d8c9c111-fbc7-44e1-94bd-1ca164370623","name":"Runaway Steam-Kin","set":"grn","collector_number":"115","rarity":"rare","booster":true,"image":"https://cards.scryfall.io/normal/front/d/8/d8c9c111-fbc7-44e1-94bd-1ca164370623.jpg?1572893254","uri":"https://scryfall.com/card/grn/115/runaway-steam-kin?utm_source=api","finishes":[{"type":"nonfoil","price":0.98},{"type":"foil","price":3.95}],"showcase":false,"extendedart":false,"inverted":false,"borderless":false,"fullart":false,"etched":false,"promo":false,"promo_types":[]},{"id":"2cc2b646-0181-4f0a-a141-00ca56069a06","name":"March of the Multitudes","set":"grn","collector_number":"188","rarity":"mythic","booster":true,"image":"https://cards.scryfall.io/normal/front/2/c/2cc2b646-0181-4f0a-a141-00ca56069a06.jpg?1572893740","uri":"https://scryfall.com/card/grn/188/march-of-the-multitudes?utm_source=api","finishes":[{"type":"nonfoil","price":0.88},{"type":"foil","price":5.19}],"showcase":false,"extendedart":false,"inverted":false,"borderless":false,"fullart":false,"etched":false,"promo":false,"promo_types":[]},{"id":"7096c9a6-2e73-41f8-b20a-b29a9f0b760c","name":"Electrostatic Field","set":"grn","collector_number":"97","rarity":"uncommon","booster":true,"image":"https://cards.scryfall.io/normal/front/7/0/7096c9a6-2e73-41f8-b20a-b29a9f0b760c.jpg?1712534108","uri":"https://scryfall.com/card/grn/97/electrostatic-field?utm_source=api","finishes":[{"type":"nonfoil","price":0.86},{"type":"foil","price":6.31}],"showcase":false,"extendedart":false,"inverted":false,"borderless":false,"fullart":false,"etched":false,"promo":false,"promo_types":[]},{"id":"a8e9f4d2-bba5-4061-8ae7-a68b912f2c11","name":"Aurelia, Exemplar of Justice","set":"grn","collector_number":"153","rarity":"mythic","booster":true,"image":"https://cards.scryfall.io/normal/front/a/8/a8e9f4d2-bba5-4061-8ae7-a68b912f2c11.jpg?1572893504","uri":"https://scryfall.com/card/grn/153/aurelia-exemplar-of-justice?utm_source=api","finishes":[{"type":"nonfoil","price":0.77},{"type":"foil","price":2.11}],"showcase":false,"extendedart":false,"inverted":false,"borderless":false,"fullart":false,"etched":false,"promo":false,"promo_types":[]},{"id":"fa36b142-e67e-49da-9080-c5994e275266","name":"Etrata, the Silencer","set":"grn","collector_number":"170","rarity":"rare","booster":true,"image":"https://cards.scryfall.io/normal/front/f/a/fa36b142-e67e-49da-9080-c5994e275266.jpg?1572893618","uri":"https://scryfall.com/card/grn/170/etrata-the-silencer?utm_source=api","finishes":[{"type":"nonfoil","price":0.66},{"type":"foil","price":3.44}],"showcase":false,"extendedart":false,"inverted":false,"borderless":false,"fullart":false,"etched":false,"promo":false,"promo_types":[]},{"id":"5e84cb9c-9876-47a4-aea4-78574321bc36","name":"Legion Warboss","set":"grn","collector_number":"109","rarity":"rare","booster":true,"image":"https://cards.scryfall.io/normal/front/5/e/5e84cb9c-9876-47a4-aea4-78574321bc36.jpg?1572893214","uri":"https://scryfall.com/card/grn/109/legion-warboss?utm_source=api","finishes":[{"type":"nonfoil","price":0.59},{"type":"foil","price":0.97}],"showcase":false,"extendedart":false,"inverted":false,"borderless":false,"fullart":false,"etched":false,"promo":false,"promo_types":[]},{"id":"bfc98428-7a0f-445f-9d48-eeb76c3e10d6","name":"Drowned Secrets","set":"grn","collector_number":"39","rarity":"rare","booster":true,"image":"https://cards.scryfall.io/normal/front/b/f/bfc98428-7a0f-445f-9d48-eeb76c3e10d6.jpg?1687687913","uri":"https://scryfall.com/card/grn/39/drowned-secrets?utm_source=api","finishes":[{"type":"nonfoil","price":0.57},{"type":"foil","price":1.16}],"showcase":false,"extendedart":false,"inverted":false,"borderless":false,"fullart":false,"etched":false,"promo":false,"promo_types":[]},{"id":"26f7cf38-78cc-4139-9f2a-4dd0be7d9da8","name":"Mausoleum Secrets","set":"grn","collector_number":"75","rarity":"rare","booster":true,"image":"https://cards.scryfall.io/normal/front/2/6/26f7cf38-78cc-4139-9f2a-4dd0be7d9da8.jpg?1572892984","uri":"https://scryfall.com/card/grn/75/mausoleum-secrets?utm_source=api","finishes":[{"type":"nonfoil","price":0.55},{"type":"foil","price":2.14}],"showcase":false,"extendedart":false,"inverted":false,"borderless":false,"fullart":false,"etched":false,"promo":false,"promo_types":[]},{"id":"c52066b3-84dc-4198-8090-3336e7df8b5d","name":"Ral, Izzet Viceroy","set":"grn","collector_number":"195","rarity":"mythic","booster":true,"image":"https://cards.scryfall.io/normal/front/c/5/c52066b3-84dc-4198-8090-3336e7df8b5d.jpg?1572893786","uri":"https://scryfall.com/card/grn/195/ral-izzet-viceroy?utm_source=api","finishes":[{"type":"nonfoil","price":0.52},{"type":"foil","price":1.68}],"showcase":false,"extendedart":false,"inverted":false,"borderless":false,"fullart":false,"etched":false,"promo":false,"promo_types":[]},{"id":"f5e6dc5f-fd83-4166-a5da-cd953722642a","name":"Impervious Greatwurm","set":"grn","collector_number":"273","rarity":"mythic","booster":false,"image":"https://cards.scryfall.io/normal/front/f/5/f5e6dc5f-fd83-4166-a5da-cd953722642a.jpg?1572894315","uri":"https://scryfall.com/card/grn/273/impervious-greatwurm?utm_source=api","finishes":[{"type":"foil","price":4.18}],"showcase":false,"extendedart":false,"inverted":false,"borderless":false,"fullart":false,"etched":false,"promo":true,"promo_types":["buyabox"]},{"id":"c44f0c60-5732-4c25-9ba9-4829f1891762","name":"Ral, Caller of Storms","set":"grn","collector_number":"265","rarity":"mythic","booster":false,"image":"https://cards.scryfall.io/normal/front/c/4/c44f0c60-5732-4c25-9ba9-4829f1891762.jpg?1572894258","uri":"https://scryfall.com/card/grn/265/ral-caller-of-storms?utm_source=api","finishes":[{"type":"foil","price":1.33}],"showcase":false,"extendedart":false,"inverted":false,"borderless":false,"fullart":false,"etched":false,"promo":false,"promo_types":["planeswalkerdeck"]},{"id":"4299dbe6-c94d-4ecc-8bfd-741d2649cba1","name":"Vraska, Regal Gorgon","set":"grn","collector_number":"269","rarity":"mythic","booster":false,"image":"https://cards.scryfall.io/normal/front/4/2/4299dbe6-c94d-4ecc-8bfd-741d2649cba1.jpg?1572894284","uri":"https://scryfall.com/card/grn/269/vraska-regal-gorgon?utm_source=api","finishes":[{"type":"foil","price":1.02}],"showcase":false,"extendedart":false,"inverted":false,"borderless":false,"fullart":false,"etched":false,"promo":false,"promo_types":["planeswalkerdeck"]},{"id":"7f918a49-a046-4115-80b8-13490ed5cd0a","name":"Mountain","set":"grn","collector_number":"263","rarity":"common","booster":false,"image":"https://cards.scryfall.io/normal/front/7/f/7f918a49-a046-4115-80b8-13490ed5cd0a.jpg?1750920744","uri":"https://scryfall.com/card/grn/263/mountain?utm_source=api","finishes":[{"type":"nonfoil","price":0.76},{"type":"foil","price":0.72}],"showcase":false,"extendedart":false,"inverted":false,"borderless":false,"fullart":false,"etched":false,"promo":false,"promo_types":["planeswalkerdeck"]},{"id":"d85892ae-dacd-4a55-a557-9db3c16017c7","name":"Forest","set":"grn","collector_number":"264","rarity":"common","booster":false,"image":"https://cards.scryfall.io/normal/front/d/8/d85892ae-dacd-4a55-a557-9db3c16017c7.jpg?1750920735","uri":"https://scryfall.com/card/grn/264/forest?utm_source=api","finishes":[{"type":"nonfoil","price":0.69},{"type":"foil","price":0.7}],"showcase":false,"extendedart":false,"inverted":false,"borderless":false,"fullart":false,"etched":false,"promo":false,"promo_types":["planeswalkerdeck"]},{"id":"bdd5a7f0-5ad3-44e8-a103-07739fd53630","name":"Swamp","set":"grn","collector_number":"262","rarity":"common","booster":false,"image":"https://cards.scryfall.io/normal/front/b/d/bdd5a7f0-5ad3-44e8-a103-07739fd53630.jpg?1750920746","uri":"https://scryfall.com/card/grn/262/swamp?utm_source=api","finishes":[{"type":"nonfoil","price":0.57},{"type":"foil","price":0.51}],"showcase":false,"extendedart":false,"inverted":false,"borderless":false,"fullart":false,"etched":false,"promo":false,"promo_types":["planeswalkerdeck"]},{"id":"29bfbf3e-3a6c-40d4-8e1b-255f429de6cc","name":"Island","set":"grn","collector_number":"261","rarity":"common","booster":false,"image":"https://cards.scryfall.io/normal/front/2/9/29bfbf3e-3a6c-40d4-8e1b-255f429de6cc.jpg?1750920748","uri":"https://scryfall.com/card/grn/261/island?utm_source=api","finishes":[{"type":"nonfoil","price":0.55},{"type":"foil","price":0.49}],"showcase":false,"extendedart":false,"inverted":false,"borderless":false,"fullart":false,"etched":false,"promo":false,"promo_types":["planeswalkerdeck"]}]}