{"set":"ori","name":"Magic Origins","updated":"2026-02-08T06:51:16.008Z","play":[{"id":"70afb856-6697-411b-b1aa-e9290a0bfd68","name":"Alhammarret's Archive","set":"ori","collector_number":"221","rarity":"mythic","booster":true,"image":"https://cards.scryfall.io/normal/front/7/0/70afb856-6697-411b-b1aa-e9290a0bfd68.jpg?1562025490","uri":"https://scryfall.com/card/ori/221/alhammarrets-archive?utm_source=api","finishes":[{"type":"nonfoil","price":17.17},{"type":"foil","price":59.07}],"showcase":false,"extendedart":false,"inverted":false,"borderless":false,"fullart":false,"etched":false,"promo":false,"promo_types":[]},{"id":"861dc1a5-4e84-47bc-83a2-f289804086d8","name":"Starfield of Nyx","set":"ori","collector_number":"33","rarity":"mythic","booster":true,"image":"https://cards.scryfall.io/normal/front/8/6/861dc1a5-4e84-47bc-83a2-f289804086d8.jpg?1562029318","uri":"https://scryfall.com/card/ori/33/starfield-of-nyx?utm_source=api","finishes":[{"type":"nonfoil","price":14.48},{"type":"foil","price":49.35}],"showcase":false,"extendedart":false,"inverted":false,"borderless":false,"fullart":false,"etched":false,"promo":false,"promo_types":[]},{"id":"cbb8edd0-4573-4b52-a3ea-83ed19dbf58d","name":"Tainted Remedy","set":"ori","collector_number":"120","rarity":"rare","booster":true,"image":"https://cards.scryfall.io/normal/front/c/b/cbb8edd0-4573-4b52-a3ea-83ed19dbf58d.jpg?1562042093","uri":"https://scryfall.com/card/ori/120/tainted-remedy?utm_source=api","finishes":[{"type":"nonfoil","price":8.79},{"type":"foil","price":11.08}],"showcase":false,"extendedart":false,"inverted":false,"borderless":false,"fullart":false,"etched":false,"promo":false,"promo_types":[]},{"id":"1af50bf1-c51e-4592-86bf-4197ec85a45d","name":"Archangel of Tithes","set":"ori","collector_number":"4","rarity":"mythic","booster":true,"image":"https://cards.scryfall.io/normal/front/1/a/1af50bf1-c51e-4592-86bf-4197ec85a45d.jpg?1562009225","uri":"https://scryfall.com/card/ori/4/archangel-of-tithes?utm_source=api","finishes":[{"type":"nonfoil","price":6.62},{"type":"foil","price":12.98}],"showcase":false,"extendedart":false,"inverted":false,"borderless":false,"fullart":false,"etched":false,"promo":false,"promo_types":[]},{"id":"f3687c36-c0ae-4dba-9379-b420236bf529","name":"Sword of the Animist","set":"ori","collector_number":"240","rarity":"rare","booster":true,"image":"https://cards.scryfall.io/normal/front/f/3/f3687c36-c0ae-4dba-9379-b420236bf529.jpg?1562049757","uri":"https://scryfall.com/card/ori/240/sword-of-the-animist?utm_source=api","finishes":[{"type":"nonfoil","price":5.98},{"type":"foil","price":16.67}],"showcase":false,"extendedart":false,"inverted":false,"borderless":false,"fullart":false,"etched":false,"promo":false,"promo_types":[]},{"id":"9f25e1cf-eeb4-458d-8fb2-b3a2f86bdd54","name":"Liliana, Heretical Healer // Liliana, Defiant Necromancer","set":"ori","collector_number":"106","rarity":"mythic","booster":true,"image":"https://cards.scryfall.io/normal/front/9/f/9f25e1cf-eeb4-458d-8fb2-b3a2f86bdd54.jpg?1562033824","uri":"https://scryfall.com/card/ori/106/liliana-heretical-healer-liliana-defiant-necromancer?utm_source=api","finishes":[{"type":"nonfoil","price":5.84},{"type":"foil","price":16.17}],"showcase":false,"extendedart":false,"inverted":false,"borderless":false,"fullart":false,"etched":false,"promo":false,"promo_types":[]},{"id":"02d6d693-f1f3-4317-bcc0-c21fa8490d38","name":"Jace, Vryn's Prodigy // Jace, Telepath Unbound","set":"ori","collector_number":"60","rarity":"mythic","booster":true,"image":"https://cards.scryfall.io/normal/front/0/2/02d6d693-f1f3-4317-bcc0-c21fa8490d38.jpg?1651492800","uri":"https://scryfall.com/card/ori/60/jace-vryns-prodigy-jace-telepath-unbound?utm_source=api","finishes":[{"type":"nonfoil","price":5.26},{"type":"foil","price":12.82}],"showcase":false,"extendedart":false,"inverted":false,"borderless":false,"fullart":false,"etched":false,"promo":false,"promo_types":[]},{"id":"7d4c90de-49aa-43ed-a18a-f7f96268e5eb","name":"Chandra's Ignition","set":"ori","collector_number":"137","rarity":"rare","booster":true,"image":"https://cards.scryfall.io/normal/front/7/d/7d4c90de-49aa-43ed-a18a-f7f96268e5eb.jpg?1562027623","uri":"https://scryfall.com/card/ori/137/chandras-ignition?utm_source=api","finishes":[{"type":"nonfoil","price":5.16},{"type":"foil","price":10.05}],"showcase":false,"extendedart":false,"inverted":false,"borderless":false,"fullart":false,"etched":false,"promo":false,"promo_types":[]},{"id":"a706d4bb-0b44-4e43-b340-7de799c086b8","name":"Woodland Bellower","set":"ori","collector_number":"207","rarity":"mythic","booster":true,"image":"https://cards.scryfall.io/normal/front/a/7/a706d4bb-0b44-4e43-b340-7de799c086b8.jpg?1562034880","uri":"https://scryfall.com/card/ori/207/woodland-bellower?utm_source=api","finishes":[{"type":"nonfoil","price":4.43},{"type":"foil","price":12.33}],"showcase":false,"extendedart":false,"inverted":false,"borderless":false,"fullart":false,"etched":false,"promo":false,"promo_types":[]},{"id":"ff0063da-ab6b-499d-8e87-8b34d46f0372","name":"Nissa, Vastwood Seer // Nissa, Sage Animist","set":"ori","collector_number":"189","rarity":"mythic","booster":true,"image":"https://cards.scryfall.io/normal/front/f/f/ff0063da-ab6b-499d-8e87-8b34d46f0372.jpg?1562209457","uri":"https://scryfall.com/card/ori/189/nissa-vastwood-seer-nissa-sage-animist?utm_source=api","finishes":[{"type":"nonfoil","price":3.84},{"type":"foil","price":4.69}],"showcase":false,"extendedart":false,"inverted":false,"borderless":false,"fullart":false,"etched":false,"promo":false,"promo_types":[]},{"id":"1ba006c8-0ffc-4e68-9a55-c7b842d3add9","name":"Helm of the Gods","set":"ori","collector_number":"230","rarity":"rare","booster":true,"image":"https://cards.scryfall.io/normal/front/1/b/1ba006c8-0ffc-4e68-9a55-c7b842d3add9.jpg?1562009618","uri":"https://scryfall.com/card/ori/230/helm-of-the-gods?utm_source=api","finishes":[{"type":"nonfoil","price":3.27},{"type":"foil","price":7}],"showcase":false,"extendedart":false,"inverted":false,"borderless":false,"fullart":false,"etched":false,"promo":false,"promo_types":[]},{"id":"b473ee0c-b037-4968-9dda-82c2288e54f7","name":"Flameshadow Conjuring","set":"ori","collector_number":"147","rarity":"rare","booster":true,"image":"https://cards.scryfall.io/normal/front/b/4/b473ee0c-b037-4968-9dda-82c2288e54f7.jpg?1562037484","uri":"https://scryfall.com/card/ori/147/flameshadow-conjuring?utm_source=api","finishes":[{"type":"nonfoil","price":3.16},{"type":"foil","price":8.21}],"showcase":false,"extendedart":false,"inverted":false,"borderless":false,"fullart":false,"etched":false,"promo":false,"promo_types":[]},{"id":"ffeca7a7-2a14-4166-9e89-0f4eb94b79f5","name":"Herald of the Pantheon","set":"ori","collector_number":"180","rarity":"rare","booster":true,"image":"https://cards.scryfall.io/normal/front/f/f/ffeca7a7-2a14-4166-9e89-0f4eb94b79f5.jpg?1562051891","uri":"https://scryfall.com/card/ori/180/herald-of-the-pantheon?utm_source=api","finishes":[{"type":"nonfoil","price":2.85},{"type":"foil","price":10.88}],"showcase":false,"extendedart":false,"inverted":false,"borderless":false,"fullart":false,"etched":false,"promo":false,"promo_types":[]},{"id":"e9df9c5e-7087-42b2-9001-c89d40a66c68","name":"Dark Petition","set":"ori","collector_number":"90","rarity":"rare","booster":true,"image":"https://cards.scryfall.io/normal/front/e/9/e9df9c5e-7087-42b2-9001-c89d40a66c68.jpg?1562047771","uri":"https://scryfall.com/card/ori/90/dark-petition?utm_source=api","finishes":[{"type":"nonfoil","price":2.83},{"type":"foil","price":4.62}],"showcase":false,"extendedart":false,"inverted":false,"borderless":false,"fullart":false,"etched":false,"promo":false,"promo_types":[]},{"id":"554a8769-c840-4c9d-9959-b075c174457b","name":"Elemental Bond","set":"ori","collector_number":"174","rarity":"uncommon","booster":true,"image":"https://cards.scryfall.io/normal/front/5/5/554a8769-c840-4c9d-9959-b075c174457b.jpg?1562020529","uri":"https://scryfall.com/card/ori/174/elemental-bond?utm_source=api","finishes":[{"type":"nonfoil","price":2.64},{"type":"foil","price":17.45}],"showcase":false,"extendedart":false,"inverted":false,"borderless":false,"fullart":false,"etched":false,"promo":false,"promo_types":[]},{"id":"b0d6caf0-4fa8-4ec5-b7f4-1307474d1b13","name":"Chandra, Fire of Kaladesh // Chandra, Roaring Flame","set":"ori","collector_number":"135","rarity":"mythic","booster":true,"image":"https://cards.scryfall.io/normal/front/b/0/b0d6caf0-4fa8-4ec5-b7f4-1307474d1b13.jpg?1562036951","uri":"https://scryfall.com/card/ori/135/chandra-fire-of-kaladesh-chandra-roaring-flame?utm_source=api","finishes":[{"type":"nonfoil","price":2.41},{"type":"foil","price":8.26}],"showcase":false,"extendedart":false,"inverted":false,"borderless":false,"fullart":false,"etched":false,"promo":false,"promo_types":[]},{"id":"4d90c3b0-f958-4a15-94a1-9bf1b0a9ac2a","name":"Sphinx's Tutelage","set":"ori","collector_number":"76","rarity":"uncommon","booster":true,"image":"https://cards.scryfall.io/normal/front/4/d/4d90c3b0-f958-4a15-94a1-9bf1b0a9ac2a.jpg?1562018976","uri":"https://scryfall.com/card/ori/76/sphinxs-tutelage?utm_source=api","finishes":[{"type":"nonfoil","price":2.32},{"type":"foil","price":6.26}],"showcase":false,"extendedart":false,"inverted":false,"borderless":false,"fullart":false,"etched":false,"promo":false,"promo_types":[]},{"id":"4b332e3d-dcf4-4f62-8130-124ec5d23b90","name":"Goblin Piledriver","set":"ori","collector_number":"151","rarity":"rare","booster":true,"image":"https://cards.scryfall.io/normal/front/4/b/4b332e3d-dcf4-4f62-8130-124ec5d23b90.jpg?1770142912","uri":"https://scryfall.com/card/ori/151/goblin-piledriver?utm_source=api","finishes":[{"type":"nonfoil","price":2.18},{"type":"foil","price":2.27}],"showcase":false,"extendedart":false,"inverted":false,"borderless":false,"fullart":false,"etched":false,"promo":false,"promo_types":[]},{"id":"1a11287a-8002-4679-9f69-a7360e7f4d3c","name":"Day's Undoing","set":"ori","collector_number":"51","rarity":"mythic","booster":true,"image":"https://cards.scryfall.io/normal/front/1/a/1a11287a-8002-4679-9f69-a7360e7f4d3c.jpg?1562009165","uri":"https://scryfall.com/card/ori/51/days-undoing?utm_source=api","finishes":[{"type":"nonfoil","price":1.79},{"type":"foil","price":9.38}],"showcase":false,"extendedart":false,"inverted":false,"borderless":false,"fullart":false,"etched":false,"promo":false,"promo_types":[]},{"id":"e3b62616-c1a3-45f7-a329-f1305c462eaf","name":"Animist's Awakening","set":"ori","collector_number":"169","rarity":"rare","booster":true,"image":"https://cards.scryfall.io/normal/front/e/3/e3b62616-c1a3-45f7-a329-f1305c462eaf.jpg?1562047014","uri":"https://scryfall.com/card/ori/169/animists-awakening?utm_source=api","finishes":[{"type":"nonfoil","price":1.66},{"type":"foil","price":5.93}],"showcase":false,"extendedart":false,"inverted":false,"borderless":false,"fullart":false,"etched":false,"promo":false,"promo_types":[]},{"id":"2465eafc-453c-4e4f-b369-0951b8a4b7bf","name":"Willbreaker","set":"ori","collector_number":"84","rarity":"rare","booster":true,"image":"https://cards.scryfall.io/normal/front/2/4/2465eafc-453c-4e4f-b369-0951b8a4b7bf.jpg?1562011291","uri":"https://scryfall.com/card/ori/84/willbreaker?utm_source=api","finishes":[{"type":"nonfoil","price":1.42},{"type":"foil","price":4.09}],"showcase":false,"extendedart":false,"inverted":false,"borderless":false,"fullart":false,"etched":false,"promo":false,"promo_types":[]},{"id":"58c39df6-b237-40d1-bdcb-2fe5d05392a9","name":"Kytheon, Hero of Akros // Gideon, Battle-Forged","set":"ori","collector_number":"23","rarity":"mythic","booster":true,"image":"https://cards.scryfall.io/normal/front/5/8/58c39df6-b237-40d1-bdcb-2fe5d05392a9.jpg?1562021001","uri":"https://scryfall.com/card/ori/23/kytheon-hero-of-akros-gideon-battle-forged?utm_source=api","finishes":[{"type":"nonfoil","price":1.39},{"type":"foil","price":6.72}],"showcase":false,"extendedart":false,"inverted":false,"borderless":false,"fullart":false,"etched":false,"promo":false,"promo_types":[]},{"id":"1a08e5ab-1ff9-4470-ab28-fea19bb79845","name":"Managorger Hydra","set":"ori","collector_number":"186","rarity":"rare","booster":true,"image":"https://cards.scryfall.io/normal/front/1/a/1a08e5ab-1ff9-4470-ab28-fea19bb79845.jpg?1562009158","uri":"https://scryfall.com/card/ori/186/managorger-hydra?utm_source=api","finishes":[{"type":"nonfoil","price":1.39},{"type":"foil","price":9.26}],"showcase":false,"extendedart":false,"inverted":false,"borderless":false,"fullart":false,"etched":false,"promo":false,"promo_types":[]},{"id":"1163ce9f-cf22-422e-a4b5-0240b88e2816","name":"Pyromancer's Goggles","set":"ori","collector_number":"236","rarity":"mythic","booster":true,"image":"https://cards.scryfall.io/normal/front/1/1/1163ce9f-cf22-422e-a4b5-0240b88e2816.jpg?1562007652","uri":"https://scryfall.com/card/ori/236/pyromancers-goggles?utm_source=api","finishes":[{"type":"nonfoil","price":1.34},{"type":"foil","price":4.82}],"showcase":false,"extendedart":false,"inverted":false,"borderless":false,"fullart":false,"etched":false,"promo":false,"promo_types":[]},{"id":"049a601d-de5c-412c-87a2-69500c08809a","name":"Knight of the White Orchid","set":"ori","collector_number":"21","rarity":"rare","booster":true,"image":"https://cards.scryfall.io/normal/front/0/4/049a601d-de5c-412c-87a2-69500c08809a.jpg?1562005143","uri":"https://scryfall.com/card/ori/21/knight-of-the-white-orchid?utm_source=api","finishes":[{"type":"nonfoil","price":1.23},{"type":"foil","price":8.18}],"showcase":false,"extendedart":false,"inverted":false,"borderless":false,"fullart":false,"etched":false,"promo":false,"promo_types":[]},{"id":"f75c0783-936d-4fa2-bdcb-01dae7a67fdb","name":"Zendikar's Roil","set":"ori","collector_number":"209","rarity":"uncommon","booster":true,"image":"https://cards.scryfall.io/normal/front/f/7/f75c0783-936d-4fa2-bdcb-01dae7a67fdb.jpg?1592470281","uri":"https://scryfall.com/card/ori/209/zendikars-roil?utm_source=api","finishes":[{"type":"nonfoil","price":1.1},{"type":"foil","price":6.64}],"showcase":false,"extendedart":false,"inverted":false,"borderless":false,"fullart":false,"etched":false,"promo":false,"promo_types":[]},{"id":"354255d7-dc29-403b-aa90-9044cde669d0","name":"Avaricious Dragon","set":"ori","collector_number":"131","rarity":"mythic","booster":true,"image":"https://cards.scryfall.io/normal/front/3/5/354255d7-dc29-403b-aa90-9044cde669d0.jpg?1562014284","uri":"https://scryfall.com/card/ori/131/avaricious-dragon?utm_source=api","finishes":[{"type":"nonfoil","price":1.01},{"type":"foil","price":5.4}],"showcase":false,"extendedart":false,"inverted":false,"borderless":false,"fullart":false,"etched":false,"promo":false,"promo_types":[]},{"id":"82c04014-91f9-4197-b4b4-f62c4739a5c2","name":"Demonic Pact","set":"ori","collector_number":"92","rarity":"mythic","booster":true,"image":"https://cards.scryfall.io/normal/front/8/2/82c04014-91f9-4197-b4b4-f62c4739a5c2.jpg?1562028673","uri":"https://scryfall.com/card/ori/92/demonic-pact?utm_source=api","finishes":[{"type":"nonfoil","price":0.81},{"type":"foil","price":13}],"showcase":false,"extendedart":false,"inverted":false,"borderless":false,"fullart":false,"etched":false,"promo":false,"promo_types":[]},{"id":"ca145c1c-537a-459e-9241-0b95368aaf3a","name":"Caves of Koilos","set":"ori","collector_number":"245","rarity":"rare","booster":true,"image":"https://cards.scryfall.io/normal/front/c/a/ca145c1c-537a-459e-9241-0b95368aaf3a.jpg?1562041630","uri":"https://scryfall.com/card/ori/245/caves-of-koilos?utm_source=api","finishes":[{"type":"nonfoil","price":0.8},{"type":"foil","price":1.99}],"showcase":false,"extendedart":false,"inverted":false,"borderless":false,"fullart":false,"etched":false,"promo":false,"promo_types":[]},{"id":"924d4025-a6f7-4ab0-8f0d-f4ba9ed0a232","name":"Llanowar Wastes","set":"ori","collector_number":"248","rarity":"rare","booster":true,"image":"https://cards.scryfall.io/normal/front/9/2/924d4025-a6f7-4ab0-8f0d-f4ba9ed0a232.jpg?1562031317","uri":"https://scryfall.com/card/ori/248/llanowar-wastes?utm_source=api","finishes":[{"type":"nonfoil","price":0.78},{"type":"foil","price":3.54}],"showcase":false,"extendedart":false,"inverted":false,"borderless":false,"fullart":false,"etched":false,"promo":false,"promo_types":[]},{"id":"f1d33afd-6f2a-43c8-ae5d-17a0674fcdd3","name":"Shivan Reef","set":"ori","collector_number":"251","rarity":"rare","booster":true,"image":"https://cards.scryfall.io/normal/front/f/1/f1d33afd-6f2a-43c8-ae5d-17a0674fcdd3.jpg?1562049659","uri":"https://scryfall.com/card/ori/251/shivan-reef?utm_source=api","finishes":[{"type":"nonfoil","price":0.75},{"type":"foil","price":2}],"showcase":false,"extendedart":false,"inverted":false,"borderless":false,"fullart":false,"etched":false,"promo":false,"promo_types":[]},{"id":"6c3fe038-a982-4cbf-a158-c45fdc3d727e","name":"Jace's Sanctum","set":"ori","collector_number":"61","rarity":"rare","booster":true,"image":"https://cards.scryfall.io/normal/front/6/c/6c3fe038-a982-4cbf-a158-c45fdc3d727e.jpg?1562024518","uri":"https://scryfall.com/card/ori/61/jaces-sanctum?utm_source=api","finishes":[{"type":"nonfoil","price":0.71},{"type":"foil","price":3.29}],"showcase":false,"extendedart":false,"inverted":false,"borderless":false,"fullart":false,"etched":false,"promo":false,"promo_types":[]},{"id":"c27f3193-3083-409e-99d8-10f5b1afe9f1","name":"Evolutionary Leap","set":"ori","collector_number":"176","rarity":"rare","booster":true,"image":"https://cards.scryfall.io/normal/front/c/2/c27f3193-3083-409e-99d8-10f5b1afe9f1.jpg?1705435017","uri":"https://scryfall.com/card/ori/176/evolutionary-leap?utm_source=api","finishes":[{"type":"nonfoil","price":0.63},{"type":"foil","price":1.91}],"showcase":false,"extendedart":false,"inverted":false,"borderless":false,"fullart":false,"etched":false,"promo":false,"promo_types":[]},{"id":"791c21fb-fc78-4106-9a42-abc73f41ab8b","name":"Hangarback Walker","set":"ori","collector_number":"229","rarity":"rare","booster":true,"image":"https://cards.scryfall.io/normal/front/7/9/791c21fb-fc78-4106-9a42-abc73f41ab8b.jpg?1562026741","uri":"https://scryfall.com/card/ori/229/hangarback-walker?utm_source=api","finishes":[{"type":"nonfoil","price":0.63},{"type":"foil","price":5.65}],"showcase":false,"extendedart":false,"inverted":false,"borderless":false,"fullart":false,"etched":false,"promo":false,"promo_types":[]},{"id":"c33ba4e5-217f-47e3-a6ce-f935a70c7566","name":"Orbs of Warding","set":"ori","collector_number":"234","rarity":"rare","booster":true,"image":"https://cards.scryfall.io/normal/front/c/3/c33ba4e5-217f-47e3-a6ce-f935a70c7566.jpg?1562040560","uri":"https://scryfall.com/card/ori/234/orbs-of-warding?utm_source=api","finishes":[{"type":"nonfoil","price":0.61},{"type":"foil","price":3.6}],"showcase":false,"extendedart":false,"inverted":false,"borderless":false,"fullart":false,"etched":false,"promo":false,"promo_types":[]},{"id":"5516d86e-539a-4ba8-8d25-1a3b27b1267a","name":"Thopter Spy Network","set":"ori","collector_number":"79","rarity":"rare","booster":true,"image":"https://cards.scryfall.io/normal/front/5/5/5516d86e-539a-4ba8-8d25-1a3b27b1267a.jpg?1562020528","uri":"https://scryfall.com/card/ori/79/thopter-spy-network?utm_source=api","finishes":[{"type":"nonfoil","price":0.56},{"type":"foil","price":5.68}],"showcase":false,"extendedart":false,"inverted":false,"borderless":false,"fullart":false,"etched":false,"promo":false,"promo_types":[]},{"id":"b1d0eb3b-00b9-42ca-9f7d-5543bffc3480","name":"The Great Aurora","set":"ori","collector_number":"179","rarity":"mythic","booster":true,"image":"https://cards.scryfall.io/normal/front/b/1/b1d0eb3b-00b9-42ca-9f7d-5543bffc3480.jpg?1562037032","uri":"https://scryfall.com/card/ori/179/the-great-aurora?utm_source=api","finishes":[{"type":"nonfoil","price":0.51},{"type":"foil","price":4.86}],"showcase":false,"extendedart":false,"inverted":false,"borderless":false,"fullart":false,"etched":false,"promo":false,"promo_types":[]}],"collector":[{"id":"70afb856-6697-411b-b1aa-e9290a0bfd68","name":"Alhammarret's Archive","set":"ori","collector_number":"221","rarity":"mythic","booster":true,"image":"https://cards.scryfall.io/normal/front/7/0/70afb856-6697-411b-b1aa-e9290a0bfd68.jpg?1562025490","uri":"https://scryfall.com/card/ori/221/alhammarrets-archive?utm_source=api","finishes":[{"type":"nonfoil","price":17.17},{"type":"foil","price":59.07}],"showcase":false,"extendedart":false,"inverted":false,"borderless":false,"fullart":false,"etched":false,"promo":false,"promo_types":[]},{"id":"861dc1a5-4e84-47bc-83a2-f289804086d8","name":"Starfield of Nyx","set":"ori","collector_number":"33","rarity":"mythic","booster":true,"image":"https://cards.scryfall.io/normal/front/8/6/861dc1a5-4e84-47bc-83a2-f289804086d8.jpg?1562029318","uri":"https://scryfall.com/card/ori/33/starfield-of-nyx?utm_source=api","finishes":[{"type":"nonfoil","price":14.48},{"type":"foil","price":49.35}],"showcase":false,"extendedart":false,"inverted":false,"borderless":false,"fullart":false,"etched":false,"promo":false,"promo_types":[]},{"id":"cbb8edd0-4573-4b52-a3ea-83ed19dbf58d","name":"Tainted Remedy","set":"ori","collector_number":"120","rarity":"rare","booster":true,"image":"https://cards.scryfall.io/normal/front/c/b/cbb8edd0-4573-4b52-a3ea-83ed19dbf58d.jpg?1562042093","uri":"https://scryfall.com/card/ori/120/tainted-remedy?utm_source=api","finishes":[{"type":"nonfoil","price":8.79},{"type":"foil","price":11.08}],"showcase":false,"extendedart":false,"inverted":false,"borderless":false,"fullart":false,"etched":false,"promo":false,"promo_types":[]},{"id":"1af50bf1-c51e-4592-86bf-4197ec85a45d","name":"Archangel of Tithes","set":"ori","collector_number":"4","rarity":"mythic","booster":true,"image":"https://cards.scryfall.io/normal/front/1/a/1af50bf1-c51e-4592-86bf-4197ec85a45d.jpg?1562009225","uri":"https://scryfall.com/card/ori/4/archangel-of-tithes?utm_source=api","finishes":[{"type":"nonfoil","price":6.62},{"type":"foil","price":12.98}],"showcase":false,"extendedart":false,"inverted":false,"borderless":false,"fullart":false,"etched":false,"promo":false,"promo_types":[]},{"id":"f3687c36-c0ae-4dba-9379-b420236bf529","name":"Sword of the Animist","set":"ori","collector_number":"240","rarity":"rare","booster":true,"image":"https://cards.scryfall.io/normal/front/f/3/f3687c36-c0ae-4dba-9379-b420236bf529.jpg?1562049757","uri":"https://scryfall.com/card/ori/240/sword-of-the-animist?utm_source=api","finishes":[{"type":"nonfoil","price":5.98},{"type":"foil","price":16.67}],"showcase":false,"extendedart":false,"inverted":false,"borderless":false,"fullart":false,"etched":false,"promo":false,"promo_types":[]},{"id":"9f25e1cf-eeb4-458d-8fb2-b3a2f86bdd54","name":"Liliana, Heretical Healer // Liliana, Defiant Necromancer","set":"ori","collector_number":"106","rarity":"mythic","booster":true,"image":"https://cards.scryfall.io/normal/front/9/f/9f25e1cf-eeb4-458d-8fb2-b3a2f86bdd54.jpg?1562033824","uri":"https://scryfall.com/card/ori/106/liliana-heretical-healer-liliana-defiant-necromancer?utm_source=api","finishes":[{"type":"nonfoil","price":5.84},{"type":"foil","price":16.17}],"showcase":false,"extendedart":false,"inverted":false,"borderless":false,"fullart":false,"etched":false,"promo":false,"promo_types":[]},{"id":"02d6d693-f1f3-4317-bcc0-c21fa8490d38","name":"Jace, Vryn's Prodigy // Jace, Telepath Unbound","set":"ori","collector_number":"60","rarity":"mythic","booster":true,"image":"https://cards.scryfall.io/normal/front/0/2/02d6d693-f1f3-4317-bcc0-c21fa8490d38.jpg?1651492800","uri":"https://scryfall.com/card/ori/60/jace-vryns-prodigy-jace-telepath-unbound?utm_source=api","finishes":[{"type":"nonfoil","price":5.26},{"type":"foil","price":12.82}],"showcase":false,"extendedart":false,"inverted":false,"borderless":false,"fullart":false,"etched":false,"promo":false,"promo_types":[]},{"id":"7d4c90de-49aa-43ed-a18a-f7f96268e5eb","name":"Chandra's Ignition","set":"ori","collector_number":"137","rarity":"rare","booster":true,"image":"https://cards.scryfall.io/normal/front/7/d/7d4c90de-49aa-43ed-a18a-f7f96268e5eb.jpg?1562027623","uri":"https://scryfall.com/card/ori/137/chandras-ignition?utm_source=api","finishes":[{"type":"nonfoil","price":5.16},{"type":"foil","price":10.05}],"showcase":false,"extendedart":false,"inverted":false,"borderless":false,"fullart":false,"etched":false,"promo":false,"promo_types":[]},{"id":"a706d4bb-0b44-4e43-b340-7de799c086b8","name":"Woodland Bellower","set":"ori","collector_number":"207","rarity":"mythic","booster":true,"image":"https://cards.scryfall.io/normal/front/a/7/a706d4bb-0b44-4e43-b340-7de799c086b8.jpg?1562034880","uri":"https://scryfall.com/card/ori/207/woodland-bellower?utm_source=api","finishes":[{"type":"nonfoil","price":4.43},{"type":"foil","price":12.33}],"showcase":false,"extendedart":false,"inverted":false,"borderless":false,"fullart":false,"etched":false,"promo":false,"promo_types":[]},{"id":"ff0063da-ab6b-499d-8e87-8b34d46f0372","name":"Nissa, Vastwood Seer // Nissa, Sage Animist","set":"ori","collector_number":"189","rarity":"mythic","booster":true,"image":"https://cards.scryfall.io/normal/front/f/f/ff0063da-ab6b-499d-8e87-8b34d46f0372.jpg?1562209457","uri":"https://scryfall.com/card/ori/189/nissa-vastwood-seer-nissa-sage-animist?utm_source=api","finishes":[{"type":"nonfoil","price":3.84},{"type":"foil","price":4.69}],"showcase":false,"extendedart":false,"inverted":false,"borderless":false,"fullart":false,"etched":false,"promo":false,"promo_types":[]},{"id":"1ba006c8-0ffc-4e68-9a55-c7b842d3add9","name":"Helm of the Gods","set":"ori","collector_number":"230","rarity":"rare","booster":true,"image":"https://cards.scryfall.io/normal/front/1/b/1ba006c8-0ffc-4e68-9a55-c7b842d3add9.jpg?1562009618","uri":"https://scryfall.com/card/ori/230/helm-of-the-gods?utm_source=api","finishes":[{"type":"nonfoil","price":3.27},{"type":"foil","price":7}],"showcase":false,"extendedart":false,"inverted":false,"borderless":false,"fullart":false,"etched":false,"promo":false,"promo_types":[]},{"id":"b473ee0c-b037-4968-9dda-82c2288e54f7","name":"Flameshadow Conjuring","set":"ori","collector_number":"147","rarity":"rare","booster":true,"image":"https://cards.scryfall.io/normal/front/b/4/b473ee0c-b037-4968-9dda-82c2288e54f7.jpg?1562037484","uri":"https://scryfall.com/card/ori/147/flameshadow-conjuring?utm_source=api","finishes":[{"type":"nonfoil","price":3.16},{"type":"foil","price":8.21}],"showcase":false,"extendedart":false,"inverted":false,"borderless":false,"fullart":false,"etched":false,"promo":false,"promo_types":[]},{"id":"ffeca7a7-2a14-4166-9e89-0f4eb94b79f5","name":"Herald of the Pantheon","set":"ori","collector_number":"180","rarity":"rare","booster":true,"image":"https://cards.scryfall.io/normal/front/f/f/ffeca7a7-2a14-4166-9e89-0f4eb94b79f5.jpg?1562051891","uri":"https://scryfall.com/card/ori/180/herald-of-the-pantheon?utm_source=api","finishes":[{"type":"nonfoil","price":2.85},{"type":"foil","price":10.88}],"showcase":false,"extendedart":false,"inverted":false,"borderless":false,"fullart":false,"etched":false,"promo":false,"promo_types":[]},{"id":"e9df9c5e-7087-42b2-9001-c89d40a66c68","name":"Dark Petition","set":"ori","collector_number":"90","rarity":"rare","booster":true,"image":"https://cards.scryfall.io/normal/front/e/9/e9df9c5e-7087-42b2-9001-c89d40a66c68.jpg?1562047771","uri":"https://scryfall.com/card/ori/90/dark-petition?utm_source=api","finishes":[{"type":"nonfoil","price":2.83},{"type":"foil","price":4.62}],"showcase":false,"extendedart":false,"inverted":false,"borderless":false,"fullart":false,"etched":false,"promo":false,"promo_types":[]},{"id":"554a8769-c840-4c9d-9959-b075c174457b","name":"Elemental Bond","set":"ori","collector_number":"174","rarity":"uncommon","booster":true,"image":"https://cards.scryfall.io/normal/front/5/5/554a8769-c840-4c9d-9959-b075c174457b.jpg?1562020529","uri":"https://scryfall.com/card/ori/174/elemental-bond?utm_source=api","finishes":[{"type":"nonfoil","price":2.64},{"type":"foil","price":17.45}],"showcase":false,"extendedart":false,"inverted":false,"borderless":false,"fullart":false,"etched":false,"promo":false,"promo_types":[]},{"id":"b0d6caf0-4fa8-4ec5-b7f4-1307474d1b13","name":"Chandra, Fire of Kaladesh // Chandra, Roaring Flame","set":"ori","collector_number":"135","rarity":"mythic","booster":true,"image":"https://cards.scryfall.io/normal/front/b/0/b0d6caf0-4fa8-4ec5-b7f4-1307474d1b13.jpg?1562036951","uri":"https://scryfall.com/card/ori/135/chandra-fire-of-kaladesh-chandra-roaring-flame?utm_source=api","finishes":[{"type":"nonfoil","price":2.41},{"type":"foil","price":8.26}],"showcase":false,"extendedart":false,"inverted":false,"borderless":false,"fullart":false,"etched":false,"promo":false,"promo_types":[]},{"id":"4d90c3b0-f958-4a15-94a1-9bf1b0a9ac2a","name":"Sphinx's Tutelage","set":"ori","collector_number":"76","rarity":"uncommon","booster":true,"image":"https://cards.scryfall.io/normal/front/4/d/4d90c3b0-f958-4a15-94a1-9bf1b0a9ac2a.jpg?1562018976","uri":"https://scryfall.com/card/ori/76/sphinxs-tutelage?utm_source=api","finishes":[{"type":"nonfoil","price":2.32},{"type":"foil","price":6.26}],"showcase":false,"extendedart":false,"inverted":false,"borderless":false,"fullart":false,"etched":false,"promo":false,"promo_types":[]},{"id":"4b332e3d-dcf4-4f62-8130-124ec5d23b90","name":"Goblin Piledriver","set":"ori","collector_number":"151","rarity":"rare","booster":true,"image":"https://cards.scryfall.io/normal/front/4/b/4b332e3d-dcf4-4f62-8130-124ec5d23b90.jpg?1770142912","uri":"https://scryfall.com/card/ori/151/goblin-piledriver?utm_source=api","finishes":[{"type":"nonfoil","price":2.18},{"type":"foil","price":2.27}],"showcase":false,"extendedart":false,"inverted":false,"borderless":false,"fullart":false,"etched":false,"promo":false,"promo_types":[]},{"id":"1a11287a-8002-4679-9f69-a7360e7f4d3c","name":"Day's Undoing","set":"ori","collector_number":"51","rarity":"mythic","booster":true,"image":"https://cards.scryfall.io/normal/front/1/a/1a11287a-8002-4679-9f69-a7360e7f4d3c.jpg?1562009165","uri":"https://scryfall.com/card/ori/51/days-undoing?utm_source=api","finishes":[{"type":"nonfoil","price":1.79},{"type":"foil","price":9.38}],"showcase":false,"extendedart":false,"inverted":false,"borderless":false,"fullart":false,"etched":false,"promo":false,"promo_types":[]},{"id":"e3b62616-c1a3-45f7-a329-f1305c462eaf","name":"Animist's Awakening","set":"ori","collector_number":"169","rarity":"rare","booster":true,"image":"https://cards.scryfall.io/normal/front/e/3/e3b62616-c1a3-45f7-a329-f1305c462eaf.jpg?1562047014","uri":"https://scryfall.com/card/ori/169/animists-awakening?utm_source=api","finishes":[{"type":"nonfoil","price":1.66},{"type":"foil","price":5.93}],"showcase":false,"extendedart":false,"inverted":false,"borderless":false,"fullart":false,"etched":false,"promo":false,"promo_types":[]},{"id":"2465eafc-453c-4e4f-b369-0951b8a4b7bf","name":"Willbreaker","set":"ori","collector_number":"84","rarity":"rare","booster":true,"image":"https://cards.scryfall.io/normal/front/2/4/2465eafc-453c-4e4f-b369-0951b8a4b7bf.jpg?1562011291","uri":"https://scryfall.com/card/ori/84/willbreaker?utm_source=api","finishes":[{"type":"nonfoil","price":1.42},{"type":"foil","price":4.09}],"showcase":false,"extendedart":false,"inverted":false,"borderless":false,"fullart":false,"etched":false,"promo":false,"promo_types":[]},{"id":"58c39df6-b237-40d1-bdcb-2fe5d05392a9","name":"Kytheon, Hero of Akros // Gideon, Battle-Forged","set":"ori","collector_number":"23","rarity":"mythic","booster":true,"image":"https://cards.scryfall.io/normal/front/5/8/58c39df6-b237-40d1-bdcb-2fe5d05392a9.jpg?1562021001","uri":"https://scryfall.com/card/ori/23/kytheon-hero-of-akros-gideon-battle-forged?utm_source=api","finishes":[{"type":"nonfoil","price":1.39},{"type":"foil","price":6.72}],"showcase":false,"extendedart":false,"inverted":false,"borderless":false,"fullart":false,"etched":false,"promo":false,"promo_types":[]},{"id":"1a08e5ab-1ff9-4470-ab28-fea19bb79845","name":"Managorger Hydra","set":"ori","collector_number":"186","rarity":"rare","booster":true,"image":"https://cards.scryfall.io/normal/front/1/a/1a08e5ab-1ff9-4470-ab28-fea19bb79845.jpg?1562009158","uri":"https://scryfall.com/card/ori/186/managorger-hydra?utm_source=api","finishes":[{"type":"nonfoil","price":1.39},{"type":"foil","price":9.26}],"showcase":false,"extendedart":false,"inverted":false,"borderless":false,"fullart":false,"etched":false,"promo":false,"promo_types":[]},{"id":"1163ce9f-cf22-422e-a4b5-0240b88e2816","name":"Pyromancer's Goggles","set":"ori","collector_number":"236","rarity":"mythic","booster":true,"image":"https://cards.scryfall.io/normal/front/1/1/1163ce9f-cf22-422e-a4b5-0240b88e2816.jpg?1562007652","uri":"https://scryfall.com/card/ori/236/pyromancers-goggles?utm_source=api","finishes":[{"type":"nonfoil","price":1.34},{"type":"foil","price":4.82}],"showcase":false,"extendedart":false,"inverted":false,"borderless":false,"fullart":false,"etched":false,"promo":false,"promo_types":[]},{"id":"049a601d-de5c-412c-87a2-69500c08809a","name":"Knight of the White Orchid","set":"ori","collector_number":"21","rarity":"rare","booster":true,"image":"https://cards.scryfall.io/normal/front/0/4/049a601d-de5c-412c-87a2-69500c08809a.jpg?1562005143","uri":"https://scryfall.com/card/ori/21/knight-of-the-white-orchid?utm_source=api","finishes":[{"type":"nonfoil","price":1.23},{"type":"foil","price":8.18}],"showcase":false,"extendedart":false,"inverted":false,"borderless":false,"fullart":false,"etched":false,"promo":false,"promo_types":[]},{"id":"f75c0783-936d-4fa2-bdcb-01dae7a67fdb","name":"Zendikar's Roil","set":"ori","collector_number":"209","rarity":"uncommon","booster":true,"image":"https://cards.scryfall.io/normal/front/f/7/f75c0783-936d-4fa2-bdcb-01dae7a67fdb.jpg?1592470281","uri":"https://scryfall.com/card/ori/209/zendikars-roil?utm_source=api","finishes":[{"type":"nonfoil","price":1.1},{"type":"foil","price":6.64}],"showcase":false,"extendedart":false,"inverted":false,"borderless":false,"fullart":false,"etched":false,"promo":false,"promo_types":[]},{"id":"354255d7-dc29-403b-aa90-9044cde669d0","name":"Avaricious Dragon","set":"ori","collector_number":"131","rarity":"mythic","booster":true,"image":"https://cards.scryfall.io/normal/front/3/5/354255d7-dc29-403b-aa90-9044cde669d0.jpg?1562014284","uri":"https://scryfall.com/card/ori/131/avaricious-dragon?utm_source=api","finishes":[{"type":"nonfoil","price":1.01},{"type":"foil","price":5.4}],"showcase":false,"extendedart":false,"inverted":false,"borderless":false,"fullart":false,"etched":false,"promo":false,"promo_types":[]},{"id":"82c04014-91f9-4197-b4b4-f62c4739a5c2","name":"Demonic Pact","set":"ori","collector_number":"92","rarity":"mythic","booster":true,"image":"https://cards.scryfall.io/normal/front/8/2/82c04014-91f9-4197-b4b4-f62c4739a5c2.jpg?1562028673","uri":"https://scryfall.com/card/ori/92/demonic-pact?utm_source=api","finishes":[{"type":"nonfoil","price":0.81},{"type":"foil","price":13}],"showcase":false,"extendedart":false,"inverted":false,"borderless":false,"fullart":false,"etched":false,"promo":false,"promo_types":[]},{"id":"ca145c1c-537a-459e-9241-0b95368aaf3a","name":"Caves of Koilos","set":"ori","collector_number":"245","rarity":"rare","booster":true,"image":"https://cards.scryfall.io/normal/front/c/a/ca145c1c-537a-459e-9241-0b95368aaf3a.jpg?1562041630","uri":"https://scryfall.com/card/ori/245/caves-of-koilos?utm_source=api","finishes":[{"type":"nonfoil","price":0.8},{"type":"foil","price":1.99}],"showcase":false,"extendedart":false,"inverted":false,"borderless":false,"fullart":false,"etched":false,"promo":false,"promo_types":[]},{"id":"924d4025-a6f7-4ab0-8f0d-f4ba9ed0a232","name":"Llanowar Wastes","set":"ori","collector_number":"248","rarity":"rare","booster":true,"image":"https://cards.scryfall.io/normal/front/9/2/924d4025-a6f7-4ab0-8f0d-f4ba9ed0a232.jpg?1562031317","uri":"https://scryfall.com/card/ori/248/llanowar-wastes?utm_source=api","finishes":[{"type":"nonfoil","price":0.78},{"type":"foil","price":3.54}],"showcase":false,"extendedart":false,"inverted":false,"borderless":false,"fullart":false,"etched":false,"promo":false,"promo_types":[]},{"id":"f1d33afd-6f2a-43c8-ae5d-17a0674fcdd3","name":"Shivan Reef","set":"ori","collector_number":"251","rarity":"rare","booster":true,"image":"https://cards.scryfall.io/normal/front/f/1/f1d33afd-6f2a-43c8-ae5d-17a0674fcdd3.jpg?1562049659","uri":"https://scryfall.com/card/ori/251/shivan-reef?utm_source=api","finishes":[{"type":"nonfoil","price":0.75},{"type":"foil","price":2}],"showcase":false,"extendedart":false,"inverted":false,"borderless":false,"fullart":false,"etched":false,"promo":false,"promo_types":[]},{"id":"6c3fe038-a982-4cbf-a158-c45fdc3d727e","name":"Jace's Sanctum","set":"ori","collector_number":"61","rarity":"rare","booster":true,"image":"https://cards.scryfall.io/normal/front/6/c/6c3fe038-a982-4cbf-a158-c45fdc3d727e.jpg?1562024518","uri":"https://scryfall.com/card/ori/61/jaces-sanctum?utm_source=api","finishes":[{"type":"nonfoil","price":0.71},{"type":"foil","price":3.29}],"showcase":false,"extendedart":false,"inverted":false,"borderless":false,"fullart":false,"etched":false,"promo":false,"promo_types":[]},{"id":"c27f3193-3083-409e-99d8-10f5b1afe9f1","name":"Evolutionary Leap","set":"ori","collector_number":"176","rarity":"rare","booster":true,"image":"https://cards.scryfall.io/normal/front/c/2/c27f3193-3083-409e-99d8-10f5b1afe9f1.jpg?1705435017","uri":"https://scryfall.com/card/ori/176/evolutionary-leap?utm_source=api","finishes":[{"type":"nonfoil","price":0.63},{"type":"foil","price":1.91}],"showcase":false,"extendedart":false,"inverted":false,"borderless":false,"fullart":false,"etched":false,"promo":false,"promo_types":[]},{"id":"791c21fb-fc78-4106-9a42-abc73f41ab8b","name":"Hangarback Walker","set":"ori","collector_number":"229","rarity":"rare","booster":true,"image":"https://cards.scryfall.io/normal/front/7/9/791c21fb-fc78-4106-9a42-abc73f41ab8b.jpg?1562026741","uri":"https://scryfall.com/card/ori/229/hangarback-walker?utm_source=api","finishes":[{"type":"nonfoil","price":0.63},{"type":"foil","price":5.65}],"showcase":false,"extendedart":false,"inverted":false,"borderless":false,"fullart":false,"etched":false,"promo":false,"promo_types":[]},{"id":"c33ba4e5-217f-47e3-a6ce-f935a70c7566","name":"Orbs of Warding","set":"ori","collector_number":"234","rarity":"rare","booster":true,"image":"https://cards.scryfall.io/normal/front/c/3/c33ba4e5-217f-47e3-a6ce-f935a70c7566.jpg?1562040560","uri":"https://scryfall.com/card/ori/234/orbs-of-warding?utm_source=api","finishes":[{"type":"nonfoil","price":0.61},{"type":"foil","price":3.6}],"showcase":false,"extendedart":false,"inverted":false,"borderless":false,"fullart":false,"etched":false,"promo":false,"promo_types":[]},{"id":"5516d86e-539a-4ba8-8d25-1a3b27b1267a","name":"Thopter Spy Network","set":"ori","collector_number":"79","rarity":"rare","booster":true,"image":"https://cards.scryfall.io/normal/front/5/5/5516d86e-539a-4ba8-8d25-1a3b27b1267a.jpg?1562020528","uri":"https://scryfall.com/card/ori/79/thopter-spy-network?utm_source=api","finishes":[{"type":"nonfoil","price":0.56},{"type":"foil","price":5.68}],"showcase":false,"extendedart":false,"inverted":false,"borderless":false,"fullart":false,"etched":false,"promo":false,"promo_types":[]},{"id":"b1d0eb3b-00b9-42ca-9f7d-5543bffc3480","name":"The Great Aurora","set":"ori","collector_number":"179","rarity":"mythic","booster":true,"image":"https://cards.scryfall.io/normal/front/b/1/b1d0eb3b-00b9-42ca-9f7d-5543bffc3480.jpg?1562037032","uri":"https://scryfall.com/card/ori/179/the-great-aurora?utm_source=api","finishes":[{"type":"nonfoil","price":0.51},{"type":"foil","price":4.86}],"showcase":false,"extendedart":false,"inverted":false,"borderless":false,"fullart":false,"etched":false,"promo":false,"promo_types":[]}]}