{"set":"vow","name":"Innistrad: Crimson Vow","updated":"2026-01-24T06:32:30.177Z","play":[{"id":"84e64f38-b1f3-47cd-8cfb-a4861369aca3","name":"Toxrill, the Corrosive","set":"vow","collector_number":"132","rarity":"mythic","booster":true,"image":"https://cards.scryfall.io/normal/front/8/4/84e64f38-b1f3-47cd-8cfb-a4861369aca3.jpg?1643590379","uri":"https://scryfall.com/card/vow/132/toxrill-the-corrosive?utm_source=api","finishes":[{"type":"nonfoil","price":15.67},{"type":"foil","price":16.6}],"showcase":false,"extendedart":false,"inverted":false,"borderless":false,"fullart":false,"etched":false,"promo":false,"promo_types":[]},{"id":"d5523659-98a8-4ae2-9ec7-d77e7352c374","name":"Deathcap Glade","set":"vow","collector_number":"261","rarity":"rare","booster":true,"image":"https://cards.scryfall.io/normal/front/d/5/d5523659-98a8-4ae2-9ec7-d77e7352c374.jpg?1655879791","uri":"https://scryfall.com/card/vow/261/deathcap-glade?utm_source=api","finishes":[{"type":"nonfoil","price":6.61},{"type":"foil","price":5.88}],"showcase":false,"extendedart":false,"inverted":false,"borderless":false,"fullart":false,"etched":false,"promo":false,"promo_types":[]},{"id":"ad44c9aa-eb8f-4200-8dfe-2af728d80083","name":"Shattered Sanctum","set":"vow","collector_number":"264","rarity":"rare","booster":true,"image":"https://cards.scryfall.io/normal/front/a/d/ad44c9aa-eb8f-4200-8dfe-2af728d80083.jpg?1655879804","uri":"https://scryfall.com/card/vow/264/shattered-sanctum?utm_source=api","finishes":[{"type":"nonfoil","price":6.19},{"type":"foil","price":4.81}],"showcase":false,"extendedart":false,"inverted":false,"borderless":false,"fullart":false,"etched":false,"promo":false,"promo_types":[]},{"id":"674c0a50-9c37-4c29-84d8-eb3e34f34d37","name":"Hallowed Haunting","set":"vow","collector_number":"17","rarity":"mythic","booster":true,"image":"https://cards.scryfall.io/normal/front/6/7/674c0a50-9c37-4c29-84d8-eb3e34f34d37.jpg?1643586385","uri":"https://scryfall.com/card/vow/17/hallowed-haunting?utm_source=api","finishes":[{"type":"nonfoil","price":5.49},{"type":"foil","price":4.68}],"showcase":false,"extendedart":false,"inverted":false,"borderless":false,"fullart":false,"etched":false,"promo":false,"promo_types":[]},{"id":"8f3fddd7-ede4-41c7-a645-a6af298a3d35","name":"Sundown Pass","set":"vow","collector_number":"266","rarity":"rare","booster":true,"image":"https://cards.scryfall.io/normal/front/8/f/8f3fddd7-ede4-41c7-a645-a6af298a3d35.jpg?1655879812","uri":"https://scryfall.com/card/vow/266/sundown-pass?utm_source=api","finishes":[{"type":"nonfoil","price":5.42},{"type":"foil","price":5.6}],"showcase":false,"extendedart":false,"inverted":false,"borderless":false,"fullart":false,"etched":false,"promo":false,"promo_types":[]},{"id":"301dacc9-ef92-4515-b907-a70d6c3fd73e","name":"Olivia, Crimson Bride","set":"vow","collector_number":"245","rarity":"mythic","booster":true,"image":"https://cards.scryfall.io/normal/front/3/0/301dacc9-ef92-4515-b907-a70d6c3fd73e.jpg?1643594300","uri":"https://scryfall.com/card/vow/245/olivia-crimson-bride?utm_source=api","finishes":[{"type":"nonfoil","price":5.4},{"type":"foil","price":6.96}],"showcase":false,"extendedart":false,"inverted":false,"borderless":false,"fullart":false,"etched":false,"promo":false,"promo_types":[]},{"id":"299f1dee-b3d7-472b-aa0b-2f9b46a96da5","name":"Stormcarved Coast","set":"vow","collector_number":"265","rarity":"rare","booster":true,"image":"https://cards.scryfall.io/normal/front/2/9/299f1dee-b3d7-472b-aa0b-2f9b46a96da5.jpg?1655879810","uri":"https://scryfall.com/card/vow/265/stormcarved-coast?utm_source=api","finishes":[{"type":"nonfoil","price":4.9},{"type":"foil","price":5.04}],"showcase":false,"extendedart":false,"inverted":false,"borderless":false,"fullart":false,"etched":false,"promo":false,"promo_types":[]},{"id":"62dffe04-c431-440d-a8da-33c74b4bb683","name":"Cultivator Colossus","set":"vow","collector_number":"195","rarity":"mythic","booster":true,"image":"https://cards.scryfall.io/normal/front/6/2/62dffe04-c431-440d-a8da-33c74b4bb683.jpg?1643592511","uri":"https://scryfall.com/card/vow/195/cultivator-colossus?utm_source=api","finishes":[{"type":"nonfoil","price":4.69},{"type":"foil","price":4.9}],"showcase":false,"extendedart":false,"inverted":false,"borderless":false,"fullart":false,"etched":false,"promo":false,"promo_types":[]},{"id":"4b546bcf-2e86-42af-bf32-81c7fd36ef8c","name":"Hullbreaker Horror","set":"vow","collector_number":"63","rarity":"rare","booster":true,"image":"https://cards.scryfall.io/normal/front/4/b/4b546bcf-2e86-42af-bf32-81c7fd36ef8c.jpg?1643587961","uri":"https://scryfall.com/card/vow/63/hullbreaker-horror?utm_source=api","finishes":[{"type":"nonfoil","price":4.44},{"type":"foil","price":4.82}],"showcase":false,"extendedart":false,"inverted":false,"borderless":false,"fullart":false,"etched":false,"promo":false,"promo_types":[]},{"id":"c0c358b4-5af2-438f-8bd5-beb0ee6b518b","name":"Avabruck Caretaker // Hollowhenge Huntmaster","set":"vow","collector_number":"187","rarity":"mythic","booster":true,"image":"https://cards.scryfall.io/normal/front/c/0/c0c358b4-5af2-438f-8bd5-beb0ee6b518b.jpg?1643592307","uri":"https://scryfall.com/card/vow/187/avabruck-caretaker-hollowhenge-huntmaster?utm_source=api","finishes":[{"type":"nonfoil","price":3.83},{"type":"foil","price":4.02}],"showcase":false,"extendedart":false,"inverted":false,"borderless":false,"fullart":false,"etched":false,"promo":false,"promo_types":[]},{"id":"9b674053-1f0f-436d-b106-f91f41cf3959","name":"Necroduality","set":"vow","collector_number":"70","rarity":"mythic","booster":true,"image":"https://cards.scryfall.io/normal/front/9/b/9b674053-1f0f-436d-b106-f91f41cf3959.jpg?1643588255","uri":"https://scryfall.com/card/vow/70/necroduality?utm_source=api","finishes":[{"type":"nonfoil","price":3.75},{"type":"foil","price":4.67}],"showcase":false,"extendedart":false,"inverted":false,"borderless":false,"fullart":false,"etched":false,"promo":false,"promo_types":[]},{"id":"63ba8eef-b834-4031-b0a1-0f8505d53813","name":"Edgar, Charmed Groom // Edgar Markov's Coffin","set":"vow","collector_number":"236","rarity":"rare","booster":true,"image":"https://cards.scryfall.io/normal/front/6/3/63ba8eef-b834-4031-b0a1-0f8505d53813.jpg?1643594071","uri":"https://scryfall.com/card/vow/236/edgar-charmed-groom-edgar-markovs-coffin?utm_source=api","finishes":[{"type":"nonfoil","price":3.68},{"type":"foil","price":4.06}],"showcase":false,"extendedart":false,"inverted":false,"borderless":false,"fullart":false,"etched":false,"promo":false,"promo_types":[]},{"id":"457086c4-1b4e-4f79-8f2a-10b16174c8bb","name":"Cemetery Gatekeeper","set":"vow","collector_number":"148","rarity":"mythic","booster":true,"image":"https://cards.scryfall.io/normal/front/4/5/457086c4-1b4e-4f79-8f2a-10b16174c8bb.jpg?1643590978","uri":"https://scryfall.com/card/vow/148/cemetery-gatekeeper?utm_source=api","finishes":[{"type":"nonfoil","price":3.21},{"type":"foil","price":2.23}],"showcase":false,"extendedart":false,"inverted":false,"borderless":false,"fullart":false,"etched":false,"promo":false,"promo_types":[]},{"id":"b124ccc4-76e3-41a4-92b2-8f1d06ea9cb8","name":"Cemetery Prowler","set":"vow","collector_number":"191","rarity":"mythic","booster":true,"image":"https://cards.scryfall.io/normal/front/b/1/b124ccc4-76e3-41a4-92b2-8f1d06ea9cb8.jpg?1643592411","uri":"https://scryfall.com/card/vow/191/cemetery-prowler?utm_source=api","finishes":[{"type":"nonfoil","price":3.19},{"type":"foil","price":4.04}],"showcase":false,"extendedart":false,"inverted":false,"borderless":false,"fullart":false,"etched":false,"promo":false,"promo_types":[]},{"id":"303ad78a-b02a-44dc-afe6-7f95781a5062","name":"Kessig Flamebreather","set":"vow","collector_number":"164","rarity":"common","booster":true,"image":"https://cards.scryfall.io/normal/front/3/0/303ad78a-b02a-44dc-afe6-7f95781a5062.jpg?1643591531","uri":"https://scryfall.com/card/vow/164/kessig-flamebreather?utm_source=api","finishes":[{"type":"nonfoil","price":2.53},{"type":"foil","price":3.84}],"showcase":false,"extendedart":false,"inverted":false,"borderless":false,"fullart":false,"etched":false,"promo":false,"promo_types":[]},{"id":"cc7ff5f4-a7cc-41a1-a22b-8cf67ad18707","name":"Sorin the Mirthless","set":"vow","collector_number":"131","rarity":"mythic","booster":true,"image":"https://cards.scryfall.io/normal/front/c/c/cc7ff5f4-a7cc-41a1-a22b-8cf67ad18707.jpg?1643590354","uri":"https://scryfall.com/card/vow/131/sorin-the-mirthless?utm_source=api","finishes":[{"type":"nonfoil","price":1.94},{"type":"foil","price":3.13}],"showcase":false,"extendedart":false,"inverted":false,"borderless":false,"fullart":false,"etched":false,"promo":false,"promo_types":[]},{"id":"608fa232-f5fe-4c58-9efe-fb780f454b19","name":"Halana and Alena, Partners","set":"vow","collector_number":"239","rarity":"rare","booster":true,"image":"https://cards.scryfall.io/normal/front/6/0/608fa232-f5fe-4c58-9efe-fb780f454b19.jpg?1643594145","uri":"https://scryfall.com/card/vow/239/halana-and-alena-partners?utm_source=api","finishes":[{"type":"nonfoil","price":1.54},{"type":"foil","price":2.16}],"showcase":false,"extendedart":false,"inverted":false,"borderless":false,"fullart":false,"etched":false,"promo":false,"promo_types":[]},{"id":"c24018e8-b8f1-44a5-9355-8b79f363569d","name":"Headless Rider","set":"vow","collector_number":"118","rarity":"rare","booster":true,"image":"https://cards.scryfall.io/normal/front/c/2/c24018e8-b8f1-44a5-9355-8b79f363569d.jpg?1643589870","uri":"https://scryfall.com/card/vow/118/headless-rider?utm_source=api","finishes":[{"type":"nonfoil","price":1.51},{"type":"foil","price":1.33}],"showcase":false,"extendedart":false,"inverted":false,"borderless":false,"fullart":false,"etched":false,"promo":false,"promo_types":[]},{"id":"946ca338-5f43-4cff-bd93-1b28449c5fdc","name":"Henrika Domnathi // Henrika, Infernal Seer","set":"vow","collector_number":"119","rarity":"mythic","booster":true,"image":"https://cards.scryfall.io/normal/front/9/4/946ca338-5f43-4cff-bd93-1b28449c5fdc.jpg?1643589923","uri":"https://scryfall.com/card/vow/119/henrika-domnathi-henrika-infernal-seer?utm_source=api","finishes":[{"type":"nonfoil","price":1.17},{"type":"foil","price":1.53}],"showcase":false,"extendedart":false,"inverted":false,"borderless":false,"fullart":false,"etched":false,"promo":false,"promo_types":[]},{"id":"a2caf73e-c3eb-4fa8-996a-d3d18b2ffaeb","name":"Glorious Sunrise","set":"vow","collector_number":"200","rarity":"rare","booster":true,"image":"https://cards.scryfall.io/normal/front/a/2/a2caf73e-c3eb-4fa8-996a-d3d18b2ffaeb.jpg?1643592660","uri":"https://scryfall.com/card/vow/200/glorious-sunrise?utm_source=api","finishes":[{"type":"nonfoil","price":1.14},{"type":"foil","price":1.58}],"showcase":false,"extendedart":false,"inverted":false,"borderless":false,"fullart":false,"etched":false,"promo":false,"promo_types":[]},{"id":"eb604455-c411-414d-a2ef-e7567ee86a4d","name":"Dreamroot Cascade","set":"vow","collector_number":"262","rarity":"rare","booster":true,"image":"https://cards.scryfall.io/normal/front/e/b/eb604455-c411-414d-a2ef-e7567ee86a4d.jpg?1655879797","uri":"https://scryfall.com/card/vow/262/dreamroot-cascade?utm_source=api","finishes":[{"type":"nonfoil","price":1.13},{"type":"foil","price":1.43}],"showcase":false,"extendedart":false,"inverted":false,"borderless":false,"fullart":false,"etched":false,"promo":false,"promo_types":[]},{"id":"681f7c73-92c6-47ba-af56-3ff032ac12da","name":"Chandra, Dressed to Kill","set":"vow","collector_number":"149","rarity":"mythic","booster":true,"image":"https://cards.scryfall.io/normal/front/6/8/681f7c73-92c6-47ba-af56-3ff032ac12da.jpg?1643596175","uri":"https://scryfall.com/card/vow/149/chandra-dressed-to-kill?utm_source=api","finishes":[{"type":"nonfoil","price":1.09},{"type":"foil","price":1.64}],"showcase":false,"extendedart":false,"inverted":false,"borderless":false,"fullart":false,"etched":false,"promo":false,"promo_types":[]},{"id":"2c9b8582-8887-4652-82e2-f9b11ee21545","name":"Undead Butler","set":"vow","collector_number":"133","rarity":"uncommon","booster":true,"image":"https://cards.scryfall.io/normal/front/2/c/2c9b8582-8887-4652-82e2-f9b11ee21545.jpg?1643590414","uri":"https://scryfall.com/card/vow/133/undead-butler?utm_source=api","finishes":[{"type":"nonfoil","price":1.07},{"type":"foil","price":0.41}],"showcase":false,"extendedart":false,"inverted":false,"borderless":false,"fullart":false,"etched":false,"promo":false,"promo_types":[]},{"id":"d8f69cea-823c-482b-a605-8138b3d950e6","name":"Welcoming Vampire","set":"vow","collector_number":"46","rarity":"rare","booster":true,"image":"https://cards.scryfall.io/normal/front/d/8/d8f69cea-823c-482b-a605-8138b3d950e6.jpg?1643587406","uri":"https://scryfall.com/card/vow/46/welcoming-vampire?utm_source=api","finishes":[{"type":"nonfoil","price":1.06},{"type":"foil","price":1.04}],"showcase":false,"extendedart":false,"inverted":false,"borderless":false,"fullart":false,"etched":false,"promo":false,"promo_types":[]},{"id":"69890076-9cc4-434f-8618-63b00fdf4515","name":"Geralf, Visionary Stitcher","set":"vow","collector_number":"61","rarity":"rare","booster":true,"image":"https://cards.scryfall.io/normal/front/6/9/69890076-9cc4-434f-8618-63b00fdf4515.jpg?1643587870","uri":"https://scryfall.com/card/vow/61/geralf-visionary-stitcher?utm_source=api","finishes":[{"type":"nonfoil","price":1.01},{"type":"foil","price":1.19}],"showcase":false,"extendedart":false,"inverted":false,"borderless":false,"fullart":false,"etched":false,"promo":false,"promo_types":[]},{"id":"a16c0871-3f40-4d5a-9d21-e7f944b64a65","name":"Voice of the Blessed","set":"vow","collector_number":"44","rarity":"rare","booster":true,"image":"https://cards.scryfall.io/normal/front/a/1/a16c0871-3f40-4d5a-9d21-e7f944b64a65.jpg?1643587335","uri":"https://scryfall.com/card/vow/44/voice-of-the-blessed?utm_source=api","finishes":[{"type":"nonfoil","price":1.01},{"type":"foil","price":1.3}],"showcase":false,"extendedart":false,"inverted":false,"borderless":false,"fullart":false,"etched":false,"promo":false,"promo_types":[]},{"id":"ca50b6a5-2e58-4de3-b0e1-0b33536f69a6","name":"Howling Moon","set":"vow","collector_number":"204","rarity":"rare","booster":true,"image":"https://cards.scryfall.io/normal/front/c/a/ca50b6a5-2e58-4de3-b0e1-0b33536f69a6.jpg?1643592864","uri":"https://scryfall.com/card/vow/204/howling-moon?utm_source=api","finishes":[{"type":"nonfoil","price":0.95},{"type":"foil","price":0.96}],"showcase":false,"extendedart":false,"inverted":false,"borderless":false,"fullart":false,"etched":false,"promo":false,"promo_types":[]},{"id":"fad4ca85-4d2d-4d1e-86ca-aa25edfcda61","name":"Splendid Reclamation","set":"vow","collector_number":"221","rarity":"rare","booster":true,"image":"https://cards.scryfall.io/normal/front/f/a/fad4ca85-4d2d-4d1e-86ca-aa25edfcda61.jpg?1643593421","uri":"https://scryfall.com/card/vow/221/splendid-reclamation?utm_source=api","finishes":[{"type":"nonfoil","price":0.8},{"type":"foil","price":2.43}],"showcase":false,"extendedart":false,"inverted":false,"borderless":false,"fullart":false,"etched":false,"promo":false,"promo_types":[]},{"id":"4abfe418-15f8-46ce-9b39-fd5a38b25d12","name":"Swamp","set":"vow","collector_number":"272","rarity":"common","booster":true,"image":"https://cards.scryfall.io/normal/front/4/a/4abfe418-15f8-46ce-9b39-fd5a38b25d12.jpg?1643595179","uri":"https://scryfall.com/card/vow/272/swamp?utm_source=api","finishes":[{"type":"nonfoil","price":0.8},{"type":"foil","price":2.24}],"showcase":true,"extendedart":false,"inverted":true,"borderless":false,"fullart":true,"etched":false,"promo":false,"promo_types":[]},{"id":"2e55a405-bf5b-4158-ba9a-239627ac9701","name":"Swamp","set":"vow","collector_number":"273","rarity":"common","booster":true,"image":"https://cards.scryfall.io/normal/front/2/e/2e55a405-bf5b-4158-ba9a-239627ac9701.jpg?1643595205","uri":"https://scryfall.com/card/vow/273/swamp?utm_source=api","finishes":[{"type":"nonfoil","price":0.8},{"type":"foil","price":1.88}],"showcase":true,"extendedart":false,"inverted":true,"borderless":false,"fullart":true,"etched":false,"promo":false,"promo_types":[]},{"id":"bec748e6-7245-4a71-aeee-cefed8346948","name":"End the Festivities","set":"vow","collector_number":"155","rarity":"common","booster":true,"image":"https://cards.scryfall.io/normal/front/b/e/bec748e6-7245-4a71-aeee-cefed8346948.jpg?1643591154","uri":"https://scryfall.com/card/vow/155/end-the-festivities?utm_source=api","finishes":[{"type":"nonfoil","price":0.73},{"type":"foil","price":1}],"showcase":false,"extendedart":false,"inverted":false,"borderless":false,"fullart":false,"etched":false,"promo":false,"promo_types":[]},{"id":"c7ceaf83-09c0-4492-a75d-4c47bd421858","name":"Howlpack Piper // Wildsong Howler","set":"vow","collector_number":"205","rarity":"rare","booster":true,"image":"https://cards.scryfall.io/normal/front/c/7/c7ceaf83-09c0-4492-a75d-4c47bd421858.jpg?1643592924","uri":"https://scryfall.com/card/vow/205/howlpack-piper-wildsong-howler?utm_source=api","finishes":[{"type":"nonfoil","price":0.66},{"type":"foil","price":0.75}],"showcase":false,"extendedart":false,"inverted":false,"borderless":false,"fullart":false,"etched":false,"promo":false,"promo_types":[]},{"id":"625b8023-2ef1-4b7b-9e48-4f774fee14e0","name":"Old Rutstein","set":"vow","collector_number":"244","rarity":"rare","booster":true,"image":"https://cards.scryfall.io/normal/front/6/2/625b8023-2ef1-4b7b-9e48-4f774fee14e0.jpg?1643594276","uri":"https://scryfall.com/card/vow/244/old-rutstein?utm_source=api","finishes":[{"type":"nonfoil","price":0.66},{"type":"foil","price":0.62}],"showcase":false,"extendedart":false,"inverted":false,"borderless":false,"fullart":false,"etched":false,"promo":false,"promo_types":[]},{"id":"c00731eb-69fe-42f3-9919-66a4cdec00f7","name":"Cemetery Protector","set":"vow","collector_number":"6","rarity":"mythic","booster":true,"image":"https://cards.scryfall.io/normal/front/c/0/c00731eb-69fe-42f3-9919-66a4cdec00f7.jpg?1643585934","uri":"https://scryfall.com/card/vow/6/cemetery-protector?utm_source=api","finishes":[{"type":"nonfoil","price":0.64},{"type":"foil","price":0.91}],"showcase":false,"extendedart":false,"inverted":false,"borderless":false,"fullart":false,"etched":false,"promo":false,"promo_types":[]},{"id":"6943c07f-ab0d-4f5a-bbe9-c0a83dc98546","name":"Reckless Impulse","set":"vow","collector_number":"174","rarity":"common","booster":true,"image":"https://cards.scryfall.io/normal/front/6/9/6943c07f-ab0d-4f5a-bbe9-c0a83dc98546.jpg?1643591880","uri":"https://scryfall.com/card/vow/174/reckless-impulse?utm_source=api","finishes":[{"type":"nonfoil","price":0.62},{"type":"foil","price":1.05}],"showcase":false,"extendedart":false,"inverted":false,"borderless":false,"fullart":false,"etched":false,"promo":false,"promo_types":[]},{"id":"7aaba76b-9cec-4c2b-b0eb-8f44201f6422","name":"Grolnok, the Omnivore","set":"vow","collector_number":"238","rarity":"rare","booster":true,"image":"https://cards.scryfall.io/normal/front/7/a/7aaba76b-9cec-4c2b-b0eb-8f44201f6422.jpg?1643594120","uri":"https://scryfall.com/card/vow/238/grolnok-the-omnivore?utm_source=api","finishes":[{"type":"nonfoil","price":0.57},{"type":"foil","price":0.76}],"showcase":false,"extendedart":false,"inverted":false,"borderless":false,"fullart":false,"etched":false,"promo":false,"promo_types":[]},{"id":"a98a208c-ee2b-4672-a43b-f4a708585b1a","name":"Kaya, Geist Hunter","set":"vow","collector_number":"240","rarity":"mythic","booster":true,"image":"https://cards.scryfall.io/normal/front/a/9/a98a208c-ee2b-4672-a43b-f4a708585b1a.jpg?1643594174","uri":"https://scryfall.com/card/vow/240/kaya-geist-hunter?utm_source=api","finishes":[{"type":"nonfoil","price":0.57},{"type":"foil","price":1.52}],"showcase":false,"extendedart":false,"inverted":false,"borderless":false,"fullart":false,"etched":false,"promo":false,"promo_types":[]},{"id":"823ad188-bd56-476d-9853-bed90bfad582","name":"Mirrorhall Mimic // Ghastly Mimicry","set":"vow","collector_number":"68","rarity":"rare","booster":true,"image":"https://cards.scryfall.io/normal/front/8/2/823ad188-bd56-476d-9853-bed90bfad582.jpg?1643588179","uri":"https://scryfall.com/card/vow/68/mirrorhall-mimic-ghastly-mimicry?utm_source=api","finishes":[{"type":"nonfoil","price":0.57},{"type":"foil","price":0.92}],"showcase":false,"extendedart":false,"inverted":false,"borderless":false,"fullart":false,"etched":false,"promo":false,"promo_types":[]},{"id":"db791fb6-b0ff-4ded-bd3d-9447cf398312","name":"Faithbound Judge // Sinner's Judgment","set":"vow","collector_number":"12","rarity":"mythic","booster":true,"image":"https://cards.scryfall.io/normal/front/d/b/db791fb6-b0ff-4ded-bd3d-9447cf398312.jpg?1739658304","uri":"https://scryfall.com/card/vow/12/faithbound-judge-sinners-judgment?utm_source=api","finishes":[{"type":"nonfoil","price":0.55},{"type":"foil","price":0.84}],"showcase":false,"extendedart":false,"inverted":false,"borderless":false,"fullart":false,"etched":false,"promo":false,"promo_types":[]},{"id":"52e59170-aa80-45e1-ad0d-ce4818e78d2a","name":"Manaform Hellkite","set":"vow","collector_number":"170","rarity":"mythic","booster":true,"image":"https://cards.scryfall.io/normal/front/5/2/52e59170-aa80-45e1-ad0d-ce4818e78d2a.jpg?1643591771","uri":"https://scryfall.com/card/vow/170/manaform-hellkite?utm_source=api","finishes":[{"type":"nonfoil","price":0.55},{"type":"foil","price":1.55}],"showcase":false,"extendedart":false,"inverted":false,"borderless":false,"fullart":false,"etched":false,"promo":false,"promo_types":[]},{"id":"0ef240aa-2a88-4ec4-888a-918466372adb","name":"Katilda, Dawnhart Martyr // Katilda's Rising Dawn","set":"vow","collector_number":"21","rarity":"rare","booster":true,"image":"https://cards.scryfall.io/normal/front/0/e/0ef240aa-2a88-4ec4-888a-918466372adb.jpg?1643586518","uri":"https://scryfall.com/card/vow/21/katilda-dawnhart-martyr-katildas-rising-dawn?utm_source=api","finishes":[{"type":"nonfoil","price":0.53},{"type":"foil","price":0.85}],"showcase":false,"extendedart":false,"inverted":false,"borderless":false,"fullart":false,"etched":false,"promo":false,"promo_types":[]},{"id":"87a02ac1-c43a-43cc-9c2b-628cfdeb4cbf","name":"Volatile Arsonist // Dire-Strain Anarchist","set":"vow","collector_number":"181","rarity":"mythic","booster":true,"image":"https://cards.scryfall.io/normal/front/8/7/87a02ac1-c43a-43cc-9c2b-628cfdeb4cbf.jpg?1739654286","uri":"https://scryfall.com/card/vow/181/volatile-arsonist-dire-strain-anarchist?utm_source=api","finishes":[{"type":"nonfoil","price":0.52},{"type":"foil","price":3.18}],"showcase":false,"extendedart":false,"inverted":false,"borderless":false,"fullart":false,"etched":false,"promo":false,"promo_types":[]},{"id":"5f619464-dc3b-4265-b4e4-2578034bf5bf","name":"Cemetery Illuminator","set":"vow","collector_number":"50","rarity":"mythic","booster":true,"image":"https://cards.scryfall.io/normal/front/5/f/5f619464-dc3b-4265-b4e4-2578034bf5bf.jpg?1643587572","uri":"https://scryfall.com/card/vow/50/cemetery-illuminator?utm_source=api","finishes":[{"type":"nonfoil","price":0.51},{"type":"foil","price":0.5}],"showcase":false,"extendedart":false,"inverted":false,"borderless":false,"fullart":false,"etched":false,"promo":false,"promo_types":[]}],"collector":[{"id":"84e64f38-b1f3-47cd-8cfb-a4861369aca3","name":"Toxrill, the Corrosive","set":"vow","collector_number":"132","rarity":"mythic","booster":true,"image":"https://cards.scryfall.io/normal/front/8/4/84e64f38-b1f3-47cd-8cfb-a4861369aca3.jpg?1643590379","uri":"https://scryfall.com/card/vow/132/toxrill-the-corrosive?utm_source=api","finishes":[{"type":"nonfoil","price":15.67},{"type":"foil","price":16.6}],"showcase":false,"extendedart":false,"inverted":false,"borderless":false,"fullart":false,"etched":false,"promo":false,"promo_types":[]},{"id":"d5523659-98a8-4ae2-9ec7-d77e7352c374","name":"Deathcap Glade","set":"vow","collector_number":"261","rarity":"rare","booster":true,"image":"https://cards.scryfall.io/normal/front/d/5/d5523659-98a8-4ae2-9ec7-d77e7352c374.jpg?1655879791","uri":"https://scryfall.com/card/vow/261/deathcap-glade?utm_source=api","finishes":[{"type":"nonfoil","price":6.61},{"type":"foil","price":5.88}],"showcase":false,"extendedart":false,"inverted":false,"borderless":false,"fullart":false,"etched":false,"promo":false,"promo_types":[]},{"id":"ad44c9aa-eb8f-4200-8dfe-2af728d80083","name":"Shattered Sanctum","set":"vow","collector_number":"264","rarity":"rare","booster":true,"image":"https://cards.scryfall.io/normal/front/a/d/ad44c9aa-eb8f-4200-8dfe-2af728d80083.jpg?1655879804","uri":"https://scryfall.com/card/vow/264/shattered-sanctum?utm_source=api","finishes":[{"type":"nonfoil","price":6.19},{"type":"foil","price":4.81}],"showcase":false,"extendedart":false,"inverted":false,"borderless":false,"fullart":false,"etched":false,"promo":false,"promo_types":[]},{"id":"674c0a50-9c37-4c29-84d8-eb3e34f34d37","name":"Hallowed Haunting","set":"vow","collector_number":"17","rarity":"mythic","booster":true,"image":"https://cards.scryfall.io/normal/front/6/7/674c0a50-9c37-4c29-84d8-eb3e34f34d37.jpg?1643586385","uri":"https://scryfall.com/card/vow/17/hallowed-haunting?utm_source=api","finishes":[{"type":"nonfoil","price":5.49},{"type":"foil","price":4.68}],"showcase":false,"extendedart":false,"inverted":false,"borderless":false,"fullart":false,"etched":false,"promo":false,"promo_types":[]},{"id":"8f3fddd7-ede4-41c7-a645-a6af298a3d35","name":"Sundown Pass","set":"vow","collector_number":"266","rarity":"rare","booster":true,"image":"https://cards.scryfall.io/normal/front/8/f/8f3fddd7-ede4-41c7-a645-a6af298a3d35.jpg?1655879812","uri":"https://scryfall.com/card/vow/266/sundown-pass?utm_source=api","finishes":[{"type":"nonfoil","price":5.42},{"type":"foil","price":5.6}],"showcase":false,"extendedart":false,"inverted":false,"borderless":false,"fullart":false,"etched":false,"promo":false,"promo_types":[]},{"id":"301dacc9-ef92-4515-b907-a70d6c3fd73e","name":"Olivia, Crimson Bride","set":"vow","collector_number":"245","rarity":"mythic","booster":true,"image":"https://cards.scryfall.io/normal/front/3/0/301dacc9-ef92-4515-b907-a70d6c3fd73e.jpg?1643594300","uri":"https://scryfall.com/card/vow/245/olivia-crimson-bride?utm_source=api","finishes":[{"type":"nonfoil","price":5.4},{"type":"foil","price":6.96}],"showcase":false,"extendedart":false,"inverted":false,"borderless":false,"fullart":false,"etched":false,"promo":false,"promo_types":[]},{"id":"299f1dee-b3d7-472b-aa0b-2f9b46a96da5","name":"Stormcarved Coast","set":"vow","collector_number":"265","rarity":"rare","booster":true,"image":"https://cards.scryfall.io/normal/front/2/9/299f1dee-b3d7-472b-aa0b-2f9b46a96da5.jpg?1655879810","uri":"https://scryfall.com/card/vow/265/stormcarved-coast?utm_source=api","finishes":[{"type":"nonfoil","price":4.9},{"type":"foil","price":5.04}],"showcase":false,"extendedart":false,"inverted":false,"borderless":false,"fullart":false,"etched":false,"promo":false,"promo_types":[]},{"id":"62dffe04-c431-440d-a8da-33c74b4bb683","name":"Cultivator Colossus","set":"vow","collector_number":"195","rarity":"mythic","booster":true,"image":"https://cards.scryfall.io/normal/front/6/2/62dffe04-c431-440d-a8da-33c74b4bb683.jpg?1643592511","uri":"https://scryfall.com/card/vow/195/cultivator-colossus?utm_source=api","finishes":[{"type":"nonfoil","price":4.69},{"type":"foil","price":4.9}],"showcase":false,"extendedart":false,"inverted":false,"borderless":false,"fullart":false,"etched":false,"promo":false,"promo_types":[]},{"id":"4b546bcf-2e86-42af-bf32-81c7fd36ef8c","name":"Hullbreaker Horror","set":"vow","collector_number":"63","rarity":"rare","booster":true,"image":"https://cards.scryfall.io/normal/front/4/b/4b546bcf-2e86-42af-bf32-81c7fd36ef8c.jpg?1643587961","uri":"https://scryfall.com/card/vow/63/hullbreaker-horror?utm_source=api","finishes":[{"type":"nonfoil","price":4.44},{"type":"foil","price":4.82}],"showcase":false,"extendedart":false,"inverted":false,"borderless":false,"fullart":false,"etched":false,"promo":false,"promo_types":[]},{"id":"c0c358b4-5af2-438f-8bd5-beb0ee6b518b","name":"Avabruck Caretaker // Hollowhenge Huntmaster","set":"vow","collector_number":"187","rarity":"mythic","booster":true,"image":"https://cards.scryfall.io/normal/front/c/0/c0c358b4-5af2-438f-8bd5-beb0ee6b518b.jpg?1643592307","uri":"https://scryfall.com/card/vow/187/avabruck-caretaker-hollowhenge-huntmaster?utm_source=api","finishes":[{"type":"nonfoil","price":3.83},{"type":"foil","price":4.02}],"showcase":false,"extendedart":false,"inverted":false,"borderless":false,"fullart":false,"etched":false,"promo":false,"promo_types":[]},{"id":"9b674053-1f0f-436d-b106-f91f41cf3959","name":"Necroduality","set":"vow","collector_number":"70","rarity":"mythic","booster":true,"image":"https://cards.scryfall.io/normal/front/9/b/9b674053-1f0f-436d-b106-f91f41cf3959.jpg?1643588255","uri":"https://scryfall.com/card/vow/70/necroduality?utm_source=api","finishes":[{"type":"nonfoil","price":3.75},{"type":"foil","price":4.67}],"showcase":false,"extendedart":false,"inverted":false,"borderless":false,"fullart":false,"etched":false,"promo":false,"promo_types":[]},{"id":"63ba8eef-b834-4031-b0a1-0f8505d53813","name":"Edgar, Charmed Groom // Edgar Markov's Coffin","set":"vow","collector_number":"236","rarity":"rare","booster":true,"image":"https://cards.scryfall.io/normal/front/6/3/63ba8eef-b834-4031-b0a1-0f8505d53813.jpg?1643594071","uri":"https://scryfall.com/card/vow/236/edgar-charmed-groom-edgar-markovs-coffin?utm_source=api","finishes":[{"type":"nonfoil","price":3.68},{"type":"foil","price":4.06}],"showcase":false,"extendedart":false,"inverted":false,"borderless":false,"fullart":false,"etched":false,"promo":false,"promo_types":[]},{"id":"457086c4-1b4e-4f79-8f2a-10b16174c8bb","name":"Cemetery Gatekeeper","set":"vow","collector_number":"148","rarity":"mythic","booster":true,"image":"https://cards.scryfall.io/normal/front/4/5/457086c4-1b4e-4f79-8f2a-10b16174c8bb.jpg?1643590978","uri":"https://scryfall.com/card/vow/148/cemetery-gatekeeper?utm_source=api","finishes":[{"type":"nonfoil","price":3.21},{"type":"foil","price":2.23}],"showcase":false,"extendedart":false,"inverted":false,"borderless":false,"fullart":false,"etched":false,"promo":false,"promo_types":[]},{"id":"b124ccc4-76e3-41a4-92b2-8f1d06ea9cb8","name":"Cemetery Prowler","set":"vow","collector_number":"191","rarity":"mythic","booster":true,"image":"https://cards.scryfall.io/normal/front/b/1/b124ccc4-76e3-41a4-92b2-8f1d06ea9cb8.jpg?1643592411","uri":"https://scryfall.com/card/vow/191/cemetery-prowler?utm_source=api","finishes":[{"type":"nonfoil","price":3.19},{"type":"foil","price":4.04}],"showcase":false,"extendedart":false,"inverted":false,"borderless":false,"fullart":false,"etched":false,"promo":false,"promo_types":[]},{"id":"303ad78a-b02a-44dc-afe6-7f95781a5062","name":"Kessig Flamebreather","set":"vow","collector_number":"164","rarity":"common","booster":true,"image":"https://cards.scryfall.io/normal/front/3/0/303ad78a-b02a-44dc-afe6-7f95781a5062.jpg?1643591531","uri":"https://scryfall.com/card/vow/164/kessig-flamebreather?utm_source=api","finishes":[{"type":"nonfoil","price":2.53},{"type":"foil","price":3.84}],"showcase":false,"extendedart":false,"inverted":false,"borderless":false,"fullart":false,"etched":false,"promo":false,"promo_types":[]},{"id":"cc7ff5f4-a7cc-41a1-a22b-8cf67ad18707","name":"Sorin the Mirthless","set":"vow","collector_number":"131","rarity":"mythic","booster":true,"image":"https://cards.scryfall.io/normal/front/c/c/cc7ff5f4-a7cc-41a1-a22b-8cf67ad18707.jpg?1643590354","uri":"https://scryfall.com/card/vow/131/sorin-the-mirthless?utm_source=api","finishes":[{"type":"nonfoil","price":1.94},{"type":"foil","price":3.13}],"showcase":false,"extendedart":false,"inverted":false,"borderless":false,"fullart":false,"etched":false,"promo":false,"promo_types":[]},{"id":"608fa232-f5fe-4c58-9efe-fb780f454b19","name":"Halana and Alena, Partners","set":"vow","collector_number":"239","rarity":"rare","booster":true,"image":"https://cards.scryfall.io/normal/front/6/0/608fa232-f5fe-4c58-9efe-fb780f454b19.jpg?1643594145","uri":"https://scryfall.com/card/vow/239/halana-and-alena-partners?utm_source=api","finishes":[{"type":"nonfoil","price":1.54},{"type":"foil","price":2.16}],"showcase":false,"extendedart":false,"inverted":false,"borderless":false,"fullart":false,"etched":false,"promo":false,"promo_types":[]},{"id":"c24018e8-b8f1-44a5-9355-8b79f363569d","name":"Headless Rider","set":"vow","collector_number":"118","rarity":"rare","booster":true,"image":"https://cards.scryfall.io/normal/front/c/2/c24018e8-b8f1-44a5-9355-8b79f363569d.jpg?1643589870","uri":"https://scryfall.com/card/vow/118/headless-rider?utm_source=api","finishes":[{"type":"nonfoil","price":1.51},{"type":"foil","price":1.33}],"showcase":false,"extendedart":false,"inverted":false,"borderless":false,"fullart":false,"etched":false,"promo":false,"promo_types":[]},{"id":"946ca338-5f43-4cff-bd93-1b28449c5fdc","name":"Henrika Domnathi // Henrika, Infernal Seer","set":"vow","collector_number":"119","rarity":"mythic","booster":true,"image":"https://cards.scryfall.io/normal/front/9/4/946ca338-5f43-4cff-bd93-1b28449c5fdc.jpg?1643589923","uri":"https://scryfall.com/card/vow/119/henrika-domnathi-henrika-infernal-seer?utm_source=api","finishes":[{"type":"nonfoil","price":1.17},{"type":"foil","price":1.53}],"showcase":false,"extendedart":false,"inverted":false,"borderless":false,"fullart":false,"etched":false,"promo":false,"promo_types":[]},{"id":"a2caf73e-c3eb-4fa8-996a-d3d18b2ffaeb","name":"Glorious Sunrise","set":"vow","collector_number":"200","rarity":"rare","booster":true,"image":"https://cards.scryfall.io/normal/front/a/2/a2caf73e-c3eb-4fa8-996a-d3d18b2ffaeb.jpg?1643592660","uri":"https://scryfall.com/card/vow/200/glorious-sunrise?utm_source=api","finishes":[{"type":"nonfoil","price":1.14},{"type":"foil","price":1.58}],"showcase":false,"extendedart":false,"inverted":false,"borderless":false,"fullart":false,"etched":false,"promo":false,"promo_types":[]},{"id":"eb604455-c411-414d-a2ef-e7567ee86a4d","name":"Dreamroot Cascade","set":"vow","collector_number":"262","rarity":"rare","booster":true,"image":"https://cards.scryfall.io/normal/front/e/b/eb604455-c411-414d-a2ef-e7567ee86a4d.jpg?1655879797","uri":"https://scryfall.com/card/vow/262/dreamroot-cascade?utm_source=api","finishes":[{"type":"nonfoil","price":1.13},{"type":"foil","price":1.43}],"showcase":false,"extendedart":false,"inverted":false,"borderless":false,"fullart":false,"etched":false,"promo":false,"promo_types":[]},{"id":"681f7c73-92c6-47ba-af56-3ff032ac12da","name":"Chandra, Dressed to Kill","set":"vow","collector_number":"149","rarity":"mythic","booster":true,"image":"https://cards.scryfall.io/normal/front/6/8/681f7c73-92c6-47ba-af56-3ff032ac12da.jpg?1643596175","uri":"https://scryfall.com/card/vow/149/chandra-dressed-to-kill?utm_source=api","finishes":[{"type":"nonfoil","price":1.09},{"type":"foil","price":1.64}],"showcase":false,"extendedart":false,"inverted":false,"borderless":false,"fullart":false,"etched":false,"promo":false,"promo_types":[]},{"id":"2c9b8582-8887-4652-82e2-f9b11ee21545","name":"Undead Butler","set":"vow","collector_number":"133","rarity":"uncommon","booster":true,"image":"https://cards.scryfall.io/normal/front/2/c/2c9b8582-8887-4652-82e2-f9b11ee21545.jpg?1643590414","uri":"https://scryfall.com/card/vow/133/undead-butler?utm_source=api","finishes":[{"type":"nonfoil","price":1.07},{"type":"foil","price":0.41}],"showcase":false,"extendedart":false,"inverted":false,"borderless":false,"fullart":false,"etched":false,"promo":false,"promo_types":[]},{"id":"d8f69cea-823c-482b-a605-8138b3d950e6","name":"Welcoming Vampire","set":"vow","collector_number":"46","rarity":"rare","booster":true,"image":"https://cards.scryfall.io/normal/front/d/8/d8f69cea-823c-482b-a605-8138b3d950e6.jpg?1643587406","uri":"https://scryfall.com/card/vow/46/welcoming-vampire?utm_source=api","finishes":[{"type":"nonfoil","price":1.06},{"type":"foil","price":1.04}],"showcase":false,"extendedart":false,"inverted":false,"borderless":false,"fullart":false,"etched":false,"promo":false,"promo_types":[]},{"id":"69890076-9cc4-434f-8618-63b00fdf4515","name":"Geralf, Visionary Stitcher","set":"vow","collector_number":"61","rarity":"rare","booster":true,"image":"https://cards.scryfall.io/normal/front/6/9/69890076-9cc4-434f-8618-63b00fdf4515.jpg?1643587870","uri":"https://scryfall.com/card/vow/61/geralf-visionary-stitcher?utm_source=api","finishes":[{"type":"nonfoil","price":1.01},{"type":"foil","price":1.19}],"showcase":false,"extendedart":false,"inverted":false,"borderless":false,"fullart":false,"etched":false,"promo":false,"promo_types":[]},{"id":"a16c0871-3f40-4d5a-9d21-e7f944b64a65","name":"Voice of the Blessed","set":"vow","collector_number":"44","rarity":"rare","booster":true,"image":"https://cards.scryfall.io/normal/front/a/1/a16c0871-3f40-4d5a-9d21-e7f944b64a65.jpg?1643587335","uri":"https://scryfall.com/card/vow/44/voice-of-the-blessed?utm_source=api","finishes":[{"type":"nonfoil","price":1.01},{"type":"foil","price":1.3}],"showcase":false,"extendedart":false,"inverted":false,"borderless":false,"fullart":false,"etched":false,"promo":false,"promo_types":[]},{"id":"ca50b6a5-2e58-4de3-b0e1-0b33536f69a6","name":"Howling Moon","set":"vow","collector_number":"204","rarity":"rare","booster":true,"image":"https://cards.scryfall.io/normal/front/c/a/ca50b6a5-2e58-4de3-b0e1-0b33536f69a6.jpg?1643592864","uri":"https://scryfall.com/card/vow/204/howling-moon?utm_source=api","finishes":[{"type":"nonfoil","price":0.95},{"type":"foil","price":0.96}],"showcase":false,"extendedart":false,"inverted":false,"borderless":false,"fullart":false,"etched":false,"promo":false,"promo_types":[]},{"id":"fad4ca85-4d2d-4d1e-86ca-aa25edfcda61","name":"Splendid Reclamation","set":"vow","collector_number":"221","rarity":"rare","booster":true,"image":"https://cards.scryfall.io/normal/front/f/a/fad4ca85-4d2d-4d1e-86ca-aa25edfcda61.jpg?1643593421","uri":"https://scryfall.com/card/vow/221/splendid-reclamation?utm_source=api","finishes":[{"type":"nonfoil","price":0.8},{"type":"foil","price":2.43}],"showcase":false,"extendedart":false,"inverted":false,"borderless":false,"fullart":false,"etched":false,"promo":false,"promo_types":[]},{"id":"4abfe418-15f8-46ce-9b39-fd5a38b25d12","name":"Swamp","set":"vow","collector_number":"272","rarity":"common","booster":true,"image":"https://cards.scryfall.io/normal/front/4/a/4abfe418-15f8-46ce-9b39-fd5a38b25d12.jpg?1643595179","uri":"https://scryfall.com/card/vow/272/swamp?utm_source=api","finishes":[{"type":"nonfoil","price":0.8},{"type":"foil","price":2.24}],"showcase":true,"extendedart":false,"inverted":true,"borderless":false,"fullart":true,"etched":false,"promo":false,"promo_types":[]},{"id":"2e55a405-bf5b-4158-ba9a-239627ac9701","name":"Swamp","set":"vow","collector_number":"273","rarity":"common","booster":true,"image":"https://cards.scryfall.io/normal/front/2/e/2e55a405-bf5b-4158-ba9a-239627ac9701.jpg?1643595205","uri":"https://scryfall.com/card/vow/273/swamp?utm_source=api","finishes":[{"type":"nonfoil","price":0.8},{"type":"foil","price":1.88}],"showcase":true,"extendedart":false,"inverted":true,"borderless":false,"fullart":true,"etched":false,"promo":false,"promo_types":[]},{"id":"bec748e6-7245-4a71-aeee-cefed8346948","name":"End the Festivities","set":"vow","collector_number":"155","rarity":"common","booster":true,"image":"https://cards.scryfall.io/normal/front/b/e/bec748e6-7245-4a71-aeee-cefed8346948.jpg?1643591154","uri":"https://scryfall.com/card/vow/155/end-the-festivities?utm_source=api","finishes":[{"type":"nonfoil","price":0.73},{"type":"foil","price":1}],"showcase":false,"extendedart":false,"inverted":false,"borderless":false,"fullart":false,"etched":false,"promo":false,"promo_types":[]},{"id":"c7ceaf83-09c0-4492-a75d-4c47bd421858","name":"Howlpack Piper // Wildsong Howler","set":"vow","collector_number":"205","rarity":"rare","booster":true,"image":"https://cards.scryfall.io/normal/front/c/7/c7ceaf83-09c0-4492-a75d-4c47bd421858.jpg?1643592924","uri":"https://scryfall.com/card/vow/205/howlpack-piper-wildsong-howler?utm_source=api","finishes":[{"type":"nonfoil","price":0.66},{"type":"foil","price":0.75}],"showcase":false,"extendedart":false,"inverted":false,"borderless":false,"fullart":false,"etched":false,"promo":false,"promo_types":[]},{"id":"625b8023-2ef1-4b7b-9e48-4f774fee14e0","name":"Old Rutstein","set":"vow","collector_number":"244","rarity":"rare","booster":true,"image":"https://cards.scryfall.io/normal/front/6/2/625b8023-2ef1-4b7b-9e48-4f774fee14e0.jpg?1643594276","uri":"https://scryfall.com/card/vow/244/old-rutstein?utm_source=api","finishes":[{"type":"nonfoil","price":0.66},{"type":"foil","price":0.62}],"showcase":false,"extendedart":false,"inverted":false,"borderless":false,"fullart":false,"etched":false,"promo":false,"promo_types":[]},{"id":"c00731eb-69fe-42f3-9919-66a4cdec00f7","name":"Cemetery Protector","set":"vow","collector_number":"6","rarity":"mythic","booster":true,"image":"https://cards.scryfall.io/normal/front/c/0/c00731eb-69fe-42f3-9919-66a4cdec00f7.jpg?1643585934","uri":"https://scryfall.com/card/vow/6/cemetery-protector?utm_source=api","finishes":[{"type":"nonfoil","price":0.64},{"type":"foil","price":0.91}],"showcase":false,"extendedart":false,"inverted":false,"borderless":false,"fullart":false,"etched":false,"promo":false,"promo_types":[]},{"id":"6943c07f-ab0d-4f5a-bbe9-c0a83dc98546","name":"Reckless Impulse","set":"vow","collector_number":"174","rarity":"common","booster":true,"image":"https://cards.scryfall.io/normal/front/6/9/6943c07f-ab0d-4f5a-bbe9-c0a83dc98546.jpg?1643591880","uri":"https://scryfall.com/card/vow/174/reckless-impulse?utm_source=api","finishes":[{"type":"nonfoil","price":0.62},{"type":"foil","price":1.05}],"showcase":false,"extendedart":false,"inverted":false,"borderless":false,"fullart":false,"etched":false,"promo":false,"promo_types":[]},{"id":"7aaba76b-9cec-4c2b-b0eb-8f44201f6422","name":"Grolnok, the Omnivore","set":"vow","collector_number":"238","rarity":"rare","booster":true,"image":"https://cards.scryfall.io/normal/front/7/a/7aaba76b-9cec-4c2b-b0eb-8f44201f6422.jpg?1643594120","uri":"https://scryfall.com/card/vow/238/grolnok-the-omnivore?utm_source=api","finishes":[{"type":"nonfoil","price":0.57},{"type":"foil","price":0.76}],"showcase":false,"extendedart":false,"inverted":false,"borderless":false,"fullart":false,"etched":false,"promo":false,"promo_types":[]},{"id":"a98a208c-ee2b-4672-a43b-f4a708585b1a","name":"Kaya, Geist Hunter","set":"vow","collector_number":"240","rarity":"mythic","booster":true,"image":"https://cards.scryfall.io/normal/front/a/9/a98a208c-ee2b-4672-a43b-f4a708585b1a.jpg?1643594174","uri":"https://scryfall.com/card/vow/240/kaya-geist-hunter?utm_source=api","finishes":[{"type":"nonfoil","price":0.57},{"type":"foil","price":1.52}],"showcase":false,"extendedart":false,"inverted":false,"borderless":false,"fullart":false,"etched":false,"promo":false,"promo_types":[]},{"id":"823ad188-bd56-476d-9853-bed90bfad582","name":"Mirrorhall Mimic // Ghastly Mimicry","set":"vow","collector_number":"68","rarity":"rare","booster":true,"image":"https://cards.scryfall.io/normal/front/8/2/823ad188-bd56-476d-9853-bed90bfad582.jpg?1643588179","uri":"https://scryfall.com/card/vow/68/mirrorhall-mimic-ghastly-mimicry?utm_source=api","finishes":[{"type":"nonfoil","price":0.57},{"type":"foil","price":0.92}],"showcase":false,"extendedart":false,"inverted":false,"borderless":false,"fullart":false,"etched":false,"promo":false,"promo_types":[]},{"id":"db791fb6-b0ff-4ded-bd3d-9447cf398312","name":"Faithbound Judge // Sinner's Judgment","set":"vow","collector_number":"12","rarity":"mythic","booster":true,"image":"https://cards.scryfall.io/normal/front/d/b/db791fb6-b0ff-4ded-bd3d-9447cf398312.jpg?1739658304","uri":"https://scryfall.com/card/vow/12/faithbound-judge-sinners-judgment?utm_source=api","finishes":[{"type":"nonfoil","price":0.55},{"type":"foil","price":0.84}],"showcase":false,"extendedart":false,"inverted":false,"borderless":false,"fullart":false,"etched":false,"promo":false,"promo_types":[]},{"id":"52e59170-aa80-45e1-ad0d-ce4818e78d2a","name":"Manaform Hellkite","set":"vow","collector_number":"170","rarity":"mythic","booster":true,"image":"https://cards.scryfall.io/normal/front/5/2/52e59170-aa80-45e1-ad0d-ce4818e78d2a.jpg?1643591771","uri":"https://scryfall.com/card/vow/170/manaform-hellkite?utm_source=api","finishes":[{"type":"nonfoil","price":0.55},{"type":"foil","price":1.55}],"showcase":false,"extendedart":false,"inverted":false,"borderless":false,"fullart":false,"etched":false,"promo":false,"promo_types":[]},{"id":"0ef240aa-2a88-4ec4-888a-918466372adb","name":"Katilda, Dawnhart Martyr // Katilda's Rising Dawn","set":"vow","collector_number":"21","rarity":"rare","booster":true,"image":"https://cards.scryfall.io/normal/front/0/e/0ef240aa-2a88-4ec4-888a-918466372adb.jpg?1643586518","uri":"https://scryfall.com/card/vow/21/katilda-dawnhart-martyr-katildas-rising-dawn?utm_source=api","finishes":[{"type":"nonfoil","price":0.53},{"type":"foil","price":0.85}],"showcase":false,"extendedart":false,"inverted":false,"borderless":false,"fullart":false,"etched":false,"promo":false,"promo_types":[]},{"id":"87a02ac1-c43a-43cc-9c2b-628cfdeb4cbf","name":"Volatile Arsonist // Dire-Strain Anarchist","set":"vow","collector_number":"181","rarity":"mythic","booster":true,"image":"https://cards.scryfall.io/normal/front/8/7/87a02ac1-c43a-43cc-9c2b-628cfdeb4cbf.jpg?1739654286","uri":"https://scryfall.com/card/vow/181/volatile-arsonist-dire-strain-anarchist?utm_source=api","finishes":[{"type":"nonfoil","price":0.52},{"type":"foil","price":3.18}],"showcase":false,"extendedart":false,"inverted":false,"borderless":false,"fullart":false,"etched":false,"promo":false,"promo_types":[]},{"id":"5f619464-dc3b-4265-b4e4-2578034bf5bf","name":"Cemetery Illuminator","set":"vow","collector_number":"50","rarity":"mythic","booster":true,"image":"https://cards.scryfall.io/normal/front/5/f/5f619464-dc3b-4265-b4e4-2578034bf5bf.jpg?1643587572","uri":"https://scryfall.com/card/vow/50/cemetery-illuminator?utm_source=api","finishes":[{"type":"nonfoil","price":0.51},{"type":"foil","price":0.5}],"showcase":false,"extendedart":false,"inverted":false,"borderless":false,"fullart":false,"etched":false,"promo":false,"promo_types":[]},{"id":"91afb4f0-70ef-4539-9081-dc130c7c63f5","name":"Swamp","set":"vow","collector_number":"410","rarity":"common","booster":false,"image":"https://cards.scryfall.io/normal/front/9/1/91afb4f0-70ef-4539-9081-dc130c7c63f5.jpg?1682292497","uri":"https://scryfall.com/card/vow/410/swamp?utm_source=api","finishes":[{"type":"etched","price":33.62}],"showcase":false,"extendedart":false,"inverted":true,"borderless":false,"fullart":true,"etched":false,"promo":true,"promo_types":["moonlitland","wizardsplaynetwork"]},{"id":"80897666-ade2-4f70-9c4d-235753b44a23","name":"Plains","set":"vow","collector_number":"408","rarity":"common","booster":false,"image":"https://cards.scryfall.io/normal/front/8/0/80897666-ade2-4f70-9c4d-235753b44a23.jpg?1682292494","uri":"https://scryfall.com/card/vow/408/plains?utm_source=api","finishes":[{"type":"etched","price":18.57}],"showcase":false,"extendedart":false,"inverted":true,"borderless":false,"fullart":true,"etched":false,"promo":true,"promo_types":["moonlitland","wizardsplaynetwork"]},{"id":"78808d46-a3a7-4598-bddf-a302977808fb","name":"Toxrill, the Corrosive","set":"vow","collector_number":"321","rarity":"mythic","booster":false,"image":"https://cards.scryfall.io/normal/front/7/8/78808d46-a3a7-4598-bddf-a302977808fb.jpg?1682717153","uri":"https://scryfall.com/card/vow/321/toxrill-the-corrosive?utm_source=api","finishes":[{"type":"nonfoil","price":15.22},{"type":"foil","price":17.34}],"showcase":true,"extendedart":false,"inverted":true,"borderless":false,"fullart":true,"etched":false,"promo":false,"promo_types":["boosterfun"]},{"id":"1fddf4cb-0680-4bc7-8bb3-cb15268aff46","name":"Island","set":"vow","collector_number":"409","rarity":"common","booster":false,"image":"https://cards.scryfall.io/normal/front/1/f/1fddf4cb-0680-4bc7-8bb3-cb15268aff46.jpg?1682292488","uri":"https://scryfall.com/card/vow/409/island?utm_source=api","finishes":[{"type":"etched","price":13.41}],"showcase":false,"extendedart":false,"inverted":true,"borderless":false,"fullart":true,"etched":false,"promo":true,"promo_types":["moonlitland","wizardsplaynetwork"]},{"id":"117716bf-43c8-4534-92da-d7948d4b5628","name":"Mountain","set":"vow","collector_number":"411","rarity":"common","booster":false,"image":"https://cards.scryfall.io/normal/front/1/1/117716bf-43c8-4534-92da-d7948d4b5628.jpg?1682292491","uri":"https://scryfall.com/card/vow/411/mountain?utm_source=api","finishes":[{"type":"etched","price":11.57}],"showcase":false,"extendedart":false,"inverted":true,"borderless":false,"fullart":true,"etched":false,"promo":true,"promo_types":["moonlitland","wizardsplaynetwork"]},{"id":"a7279281-42d5-4226-b841-f1f4deff919b","name":"Forest","set":"vow","collector_number":"412","rarity":"common","booster":false,"image":"https://cards.scryfall.io/normal/front/a/7/a7279281-42d5-4226-b841-f1f4deff919b.jpg?1682292480","uri":"https://scryfall.com/card/vow/412/forest?utm_source=api","finishes":[{"type":"etched","price":11.42}],"showcase":false,"extendedart":false,"inverted":true,"borderless":false,"fullart":true,"etched":false,"promo":true,"promo_types":["moonlitland","wizardsplaynetwork"]},{"id":"7964ed78-c0c2-4555-bc25-b0eac14d0b34","name":"Olivia, Crimson Bride","set":"vow","collector_number":"315","rarity":"mythic","booster":false,"image":"https://cards.scryfall.io/normal/front/7/9/7964ed78-c0c2-4555-bc25-b0eac14d0b34.jpg?1645055336","uri":"https://scryfall.com/card/vow/315/olivia-crimson-bride?utm_source=api","finishes":[{"type":"nonfoil","price":9.5},{"type":"foil","price":19.37}],"showcase":true,"extendedart":false,"inverted":false,"borderless":false,"fullart":false,"etched":false,"promo":false,"promo_types":["boosterfun"]},{"id":"619474c0-2978-4152-9943-292707d99fb3","name":"Deathcap Glade","set":"vow","collector_number":"281","rarity":"rare","booster":false,"image":"https://cards.scryfall.io/normal/front/6/1/619474c0-2978-4152-9943-292707d99fb3.jpg?1682717766","uri":"https://scryfall.com/card/vow/281/deathcap-glade?utm_source=api","finishes":[{"type":"nonfoil","price":8.13},{"type":"foil","price":9.54}],"showcase":false,"extendedart":false,"inverted":true,"borderless":true,"fullart":true,"etched":false,"promo":false,"promo_types":["boosterfun"]},{"id":"400ca655-68ed-4714-96e9-55df00a325b3","name":"Necroduality","set":"vow","collector_number":"362","rarity":"mythic","booster":false,"image":"https://cards.scryfall.io/normal/front/4/0/400ca655-68ed-4714-96e9-55df00a325b3.jpg?1646534562","uri":"https://scryfall.com/card/vow/362/necroduality?utm_source=api","finishes":[{"type":"nonfoil","price":8.06},{"type":"foil","price":10.35}],"showcase":false,"extendedart":true,"inverted":false,"borderless":false,"fullart":false,"etched":false,"promo":false,"promo_types":["boosterfun"]},{"id":"9885da74-30bd-461d-98ca-0dc72d817dbd","name":"Shattered Sanctum","set":"vow","collector_number":"283","rarity":"rare","booster":false,"image":"https://cards.scryfall.io/normal/front/9/8/9885da74-30bd-461d-98ca-0dc72d817dbd.jpg?1682717776","uri":"https://scryfall.com/card/vow/283/shattered-sanctum?utm_source=api","finishes":[{"type":"nonfoil","price":7.32},{"type":"foil","price":11.01}],"showcase":false,"extendedart":false,"inverted":true,"borderless":true,"fullart":true,"etched":false,"promo":false,"promo_types":["boosterfun"]},{"id":"5f1e7d34-f250-4a61-a95b-75450d134eec","name":"Sundown Pass","set":"vow","collector_number":"285","rarity":"rare","booster":false,"image":"https://cards.scryfall.io/normal/front/5/f/5f1e7d34-f250-4a61-a95b-75450d134eec.jpg?1682717789","uri":"https://scryfall.com/card/vow/285/sundown-pass?utm_source=api","finishes":[{"type":"nonfoil","price":7.23},{"type":"foil","price":8.63}],"showcase":false,"extendedart":false,"inverted":true,"borderless":true,"fullart":true,"etched":false,"promo":false,"promo_types":["boosterfun"]},{"id":"51089813-8ad5-4ee0-af75-cfba870b675c","name":"Sorin the Mirthless","set":"vow","collector_number":"297","rarity":"mythic","booster":false,"image":"https://cards.scryfall.io/normal/front/5/1/51089813-8ad5-4ee0-af75-cfba870b675c.jpg?1645054887","uri":"https://scryfall.com/card/vow/297/sorin-the-mirthless?utm_source=api","finishes":[{"type":"nonfoil","price":6.62},{"type":"foil","price":21.19}],"showcase":true,"extendedart":false,"inverted":false,"borderless":false,"fullart":false,"etched":false,"promo":false,"promo_types":["boosterfun"]},{"id":"0d5552d3-6860-42e5-8a13-1d36dce77322","name":"Olivia, Crimson Bride","set":"vow","collector_number":"343","rarity":"mythic","booster":false,"image":"https://cards.scryfall.io/normal/front/0/d/0d5552d3-6860-42e5-8a13-1d36dce77322.jpg?1645234877","uri":"https://scryfall.com/card/vow/343/olivia-crimson-bride?utm_source=api","finishes":[{"type":"nonfoil","price":6.44},{"type":"foil","price":7.23}],"showcase":false,"extendedart":false,"inverted":true,"borderless":true,"fullart":true,"etched":false,"promo":false,"promo_types":["draculaseries","boosterfun"]},{"id":"2e073047-fba8-41bd-b260-1eefb084fc80","name":"Hullbreaker Horror","set":"vow","collector_number":"359","rarity":"rare","booster":false,"image":"https://cards.scryfall.io/normal/front/2/e/2e073047-fba8-41bd-b260-1eefb084fc80.jpg?1693965987","uri":"https://scryfall.com/card/vow/359/hullbreaker-horror?utm_source=api","finishes":[{"type":"nonfoil","price":6.16},{"type":"foil","price":5.34}],"showcase":false,"extendedart":true,"inverted":false,"borderless":false,"fullart":false,"etched":false,"promo":false,"promo_types":["boosterfun"]},{"id":"9d752b67-93ea-4f76-ad80-09787427398e","name":"Cultivator Colossus","set":"vow","collector_number":"386","rarity":"mythic","booster":false,"image":"https://cards.scryfall.io/normal/front/9/d/9d752b67-93ea-4f76-ad80-09787427398e.jpg?1646615927","uri":"https://scryfall.com/card/vow/386/cultivator-colossus?utm_source=api","finishes":[{"type":"nonfoil","price":5.78},{"type":"foil","price":7.14}],"showcase":false,"extendedart":true,"inverted":false,"borderless":false,"fullart":false,"etched":false,"promo":false,"promo_types":["boosterfun"]},{"id":"260d784d-0213-44da-8f78-58968a185012","name":"Sorin the Mirthless","set":"vow","collector_number":"337","rarity":"mythic","booster":false,"image":"https://cards.scryfall.io/normal/front/2/6/260d784d-0213-44da-8f78-58968a185012.jpg?1645227319","uri":"https://scryfall.com/card/vow/337/sorin-the-mirthless?utm_source=api","finishes":[{"type":"nonfoil","price":5.66},{"type":"foil","price":7.44}],"showcase":false,"extendedart":false,"inverted":true,"borderless":true,"fullart":true,"etched":false,"promo":false,"promo_types":["draculaseries","boosterfun"]},{"id":"d0904640-40e8-45bf-ac9c-94b1dd0bab8f","name":"Hallowed Haunting","set":"vow","collector_number":"349","rarity":"mythic","booster":false,"image":"https://cards.scryfall.io/normal/front/d/0/d0904640-40e8-45bf-ac9c-94b1dd0bab8f.jpg?1646449533","uri":"https://scryfall.com/card/vow/349/hallowed-haunting?utm_source=api","finishes":[{"type":"nonfoil","price":5.61},{"type":"foil","price":6.35}],"showcase":false,"extendedart":true,"inverted":false,"borderless":false,"fullart":false,"etched":false,"promo":false,"promo_types":["boosterfun"]},{"id":"3e589848-2c25-43e8-a940-7769f7936815","name":"Stormcarved Coast","set":"vow","collector_number":"284","rarity":"rare","booster":false,"image":"https://cards.scryfall.io/normal/front/3/e/3e589848-2c25-43e8-a940-7769f7936815.jpg?1682717783","uri":"https://scryfall.com/card/vow/284/stormcarved-coast?utm_source=api","finishes":[{"type":"nonfoil","price":5.53},{"type":"foil","price":7.98}],"showcase":false,"extendedart":false,"inverted":true,"borderless":true,"fullart":true,"etched":false,"promo":false,"promo_types":["boosterfun"]},{"id":"7352dcf9-fcdf-45c2-a581-87c5ec965618","name":"Cemetery Prowler","set":"vow","collector_number":"385","rarity":"mythic","booster":false,"image":"https://cards.scryfall.io/normal/front/7/3/7352dcf9-fcdf-45c2-a581-87c5ec965618.jpg?1646615893","uri":"https://scryfall.com/card/vow/385/cemetery-prowler?utm_source=api","finishes":[{"type":"nonfoil","price":5.42},{"type":"foil","price":5.73}],"showcase":false,"extendedart":true,"inverted":false,"borderless":false,"fullart":false,"etched":false,"promo":false,"promo_types":["boosterfun"]},{"id":"10732397-68eb-4f1d-a2e6-10479f66805f","name":"Edgar, Charmed Groom // Edgar Markov's Coffin","set":"vow","collector_number":"341","rarity":"rare","booster":false,"image":"https://cards.scryfall.io/normal/front/1/0/10732397-68eb-4f1d-a2e6-10479f66805f.jpg?1645228915","uri":"https://scryfall.com/card/vow/341/edgar-charmed-groom-edgar-markovs-coffin?utm_source=api","finishes":[{"type":"nonfoil","price":5.23},{"type":"foil","price":5.33}],"showcase":false,"extendedart":false,"inverted":true,"borderless":true,"fullart":true,"etched":false,"promo":false,"promo_types":["draculaseries","boosterfun"]},{"id":"6b525a96-17cb-427e-a88b-484e23f78537","name":"Avabruck Caretaker // Hollowhenge Huntmaster","set":"vow","collector_number":"384","rarity":"mythic","booster":false,"image":"https://cards.scryfall.io/normal/front/6/b/6b525a96-17cb-427e-a88b-484e23f78537.jpg?1646615882","uri":"https://scryfall.com/card/vow/384/avabruck-caretaker-hollowhenge-huntmaster?utm_source=api","finishes":[{"type":"nonfoil","price":5.17},{"type":"foil","price":5.92}],"showcase":false,"extendedart":true,"inverted":false,"borderless":false,"fullart":false,"etched":false,"promo":false,"promo_types":["boosterfun"]},{"id":"544d7162-b78f-4a70-86e7-83cec7062039","name":"Headless Rider","set":"vow","collector_number":"372","rarity":"rare","booster":false,"image":"https://cards.scryfall.io/normal/front/5/4/544d7162-b78f-4a70-86e7-83cec7062039.jpg?1646536116","uri":"https://scryfall.com/card/vow/372/headless-rider?utm_source=api","finishes":[{"type":"nonfoil","price":5.13},{"type":"foil","price":4.1}],"showcase":false,"extendedart":true,"inverted":false,"borderless":false,"fullart":false,"etched":false,"promo":false,"promo_types":["boosterfun"]},{"id":"aafe47a8-0223-4c0b-b6ce-e25446a07c96","name":"Henrika Domnathi // Henrika, Infernal Seer","set":"vow","collector_number":"335","rarity":"mythic","booster":false,"image":"https://cards.scryfall.io/normal/front/a/a/aafe47a8-0223-4c0b-b6ce-e25446a07c96.jpg?1645065945","uri":"https://scryfall.com/card/vow/335/henrika-domnathi-henrika-infernal-seer?utm_source=api","finishes":[{"type":"nonfoil","price":4.44},{"type":"foil","price":4.3}],"showcase":false,"extendedart":false,"inverted":true,"borderless":true,"fullart":true,"etched":false,"promo":false,"promo_types":["draculaseries","boosterfun"]},{"id":"0bbfdaf0-6507-4c46-afe1-b4281a645cbf","name":"Splendid Reclamation","set":"vow","collector_number":"393","rarity":"rare","booster":false,"image":"https://cards.scryfall.io/normal/front/0/b/0bbfdaf0-6507-4c46-afe1-b4281a645cbf.jpg?1646616005","uri":"https://scryfall.com/card/vow/393/splendid-reclamation?utm_source=api","finishes":[{"type":"nonfoil","price":4.41},{"type":"foil","price":6.27}],"showcase":false,"extendedart":true,"inverted":false,"borderless":false,"fullart":false,"etched":false,"promo":false,"promo_types":["boosterfun"]},{"id":"7129a358-4628-4426-ae3b-e3d9288a6355","name":"Chandra, Dressed to Kill","set":"vow","collector_number":"279","rarity":"mythic","booster":false,"image":"https://cards.scryfall.io/normal/front/7/1/7129a358-4628-4426-ae3b-e3d9288a6355.jpg?1643597140","uri":"https://scryfall.com/card/vow/279/chandra-dressed-to-kill?utm_source=api","finishes":[{"type":"nonfoil","price":3.78},{"type":"foil","price":7.12}],"showcase":false,"extendedart":false,"inverted":false,"borderless":true,"fullart":true,"etched":false,"promo":false,"promo_types":["boosterfun"]},{"id":"112394a6-7819-43b4-adad-f6900aff2936","name":"Sorin the Mirthless","set":"vow","collector_number":"278","rarity":"mythic","booster":false,"image":"https://cards.scryfall.io/normal/front/1/1/112394a6-7819-43b4-adad-f6900aff2936.jpg?1643597114","uri":"https://scryfall.com/card/vow/278/sorin-the-mirthless?utm_source=api","finishes":[{"type":"nonfoil","price":3.61},{"type":"foil","price":5.11}],"showcase":false,"extendedart":false,"inverted":false,"borderless":true,"fullart":true,"etched":false,"promo":false,"promo_types":["boosterfun"]},{"id":"7abf10e9-6f06-4424-b156-dd03e4d3e4f6","name":"Edgar, Charmed Groom // Edgar Markov's Coffin","set":"vow","collector_number":"311","rarity":"rare","booster":false,"image":"https://cards.scryfall.io/normal/front/7/a/7abf10e9-6f06-4424-b156-dd03e4d3e4f6.jpg?1645055251","uri":"https://scryfall.com/card/vow/311/edgar-charmed-groom-edgar-markovs-coffin?utm_source=api","finishes":[{"type":"nonfoil","price":3.6},{"type":"foil","price":4.39}],"showcase":true,"extendedart":false,"inverted":false,"borderless":false,"fullart":false,"etched":false,"promo":false,"promo_types":["boosterfun"]},{"id":"2997c3b1-0255-41be-9189-03da53838f63","name":"Dreamroot Cascade","set":"vow","collector_number":"282","rarity":"rare","booster":false,"image":"https://cards.scryfall.io/normal/front/2/9/2997c3b1-0255-41be-9189-03da53838f63.jpg?1682717771","uri":"https://scryfall.com/card/vow/282/dreamroot-cascade?utm_source=api","finishes":[{"type":"nonfoil","price":3.3},{"type":"foil","price":6.52}],"showcase":false,"extendedart":false,"inverted":true,"borderless":true,"fullart":true,"etched":false,"promo":false,"promo_types":["boosterfun"]},{"id":"952bd18f-29f0-422e-a28e-4fc7ce21b9c9","name":"Glorious Sunrise","set":"vow","collector_number":"388","rarity":"rare","booster":false,"image":"https://cards.scryfall.io/normal/front/9/5/952bd18f-29f0-422e-a28e-4fc7ce21b9c9.jpg?1646615950","uri":"https://scryfall.com/card/vow/388/glorious-sunrise?utm_source=api","finishes":[{"type":"nonfoil","price":2.82},{"type":"foil","price":3.58}],"showcase":false,"extendedart":true,"inverted":false,"borderless":false,"fullart":false,"etched":false,"promo":false,"promo_types":["boosterfun"]},{"id":"43ec9524-0958-4ce5-b521-ce38dd54a9d1","name":"Voldaren Estate","set":"vow","collector_number":"403","rarity":"rare","booster":false,"image":"https://cards.scryfall.io/normal/front/4/3/43ec9524-0958-4ce5-b521-ce38dd54a9d1.jpg?1682717283","uri":"https://scryfall.com/card/vow/403/voldaren-estate?utm_source=api","finishes":[{"type":"foil","price":2.73}],"showcase":false,"extendedart":false,"inverted":true,"borderless":true,"fullart":true,"etched":false,"promo":true,"promo_types":["draculaseries","buyabox"]},{"id":"d008aac8-0e84-49ae-8905-68db2b2900ef","name":"Voice of the Blessed","set":"vow","collector_number":"354","rarity":"rare","booster":false,"image":"https://cards.scryfall.io/normal/front/d/0/d008aac8-0e84-49ae-8905-68db2b2900ef.jpg?1646449729","uri":"https://scryfall.com/card/vow/354/voice-of-the-blessed?utm_source=api","finishes":[{"type":"nonfoil","price":2.72},{"type":"foil","price":2.79}],"showcase":false,"extendedart":true,"inverted":false,"borderless":false,"fullart":false,"etched":false,"promo":false,"promo_types":["boosterfun"]},{"id":"0954ed3d-a5d8-4330-b07c-bf3e51192e4b","name":"Voldaren Bloodcaster // Bloodbat Summoner","set":"vow","collector_number":"338","rarity":"rare","booster":false,"image":"https://cards.scryfall.io/normal/front/0/9/0954ed3d-a5d8-4330-b07c-bf3e51192e4b.jpg?1645227339","uri":"https://scryfall.com/card/vow/338/voldaren-bloodcaster-bloodbat-summoner?utm_source=api","finishes":[{"type":"nonfoil","price":2.62},{"type":"foil","price":2.66}],"showcase":false,"extendedart":false,"inverted":true,"borderless":true,"fullart":true,"etched":false,"promo":false,"promo_types":["draculaseries","boosterfun"]},{"id":"63141c56-f0dd-4bb3-808d-6b7031253cad","name":"Cemetery Gatekeeper","set":"vow","collector_number":"304","rarity":"mythic","booster":false,"image":"https://cards.scryfall.io/normal/front/6/3/63141c56-f0dd-4bb3-808d-6b7031253cad.jpg?1645055083","uri":"https://scryfall.com/card/vow/304/cemetery-gatekeeper?utm_source=api","finishes":[{"type":"nonfoil","price":2.02},{"type":"foil","price":2.89}],"showcase":true,"extendedart":false,"inverted":false,"borderless":false,"fullart":false,"etched":false,"promo":false,"promo_types":["boosterfun"]},{"id":"69c8f0f2-3694-4f82-9e45-0130248875ea","name":"Manaform Hellkite","set":"vow","collector_number":"380","rarity":"mythic","booster":false,"image":"https://cards.scryfall.io/normal/front/6/9/69c8f0f2-3694-4f82-9e45-0130248875ea.jpg?1646612926","uri":"https://scryfall.com/card/vow/380/manaform-hellkite?utm_source=api","finishes":[{"type":"nonfoil","price":2.02},{"type":"foil","price":3.43}],"showcase":false,"extendedart":true,"inverted":false,"borderless":false,"fullart":false,"etched":false,"promo":false,"promo_types":["boosterfun"]},{"id":"fd60ee8d-fb50-41df-89a8-aed5a53d755f","name":"Welcoming Vampire","set":"vow","collector_number":"287","rarity":"rare","booster":false,"image":"https://cards.scryfall.io/normal/front/f/d/fd60ee8d-fb50-41df-89a8-aed5a53d755f.jpg?1645054612","uri":"https://scryfall.com/card/vow/287/welcoming-vampire?utm_source=api","finishes":[{"type":"nonfoil","price":1.69},{"type":"foil","price":4.4}],"showcase":true,"extendedart":false,"inverted":false,"borderless":false,"fullart":false,"etched":false,"promo":false,"promo_types":["boosterfun"]},{"id":"e86c212a-180d-4fd5-94d0-c0c946683f00","name":"Kaya, Geist Hunter","set":"vow","collector_number":"280","rarity":"mythic","booster":false,"image":"https://cards.scryfall.io/normal/front/e/8/e86c212a-180d-4fd5-94d0-c0c946683f00.jpg?1643597166","uri":"https://scryfall.com/card/vow/280/kaya-geist-hunter?utm_source=api","finishes":[{"type":"nonfoil","price":1.48},{"type":"foil","price":3.55}],"showcase":false,"extendedart":false,"inverted":false,"borderless":true,"fullart":true,"etched":false,"promo":false,"promo_types":["boosterfun"]},{"id":"2699d2a8-8f17-42d2-9eb2-8c1ab8dda6c4","name":"Faithbound Judge // Sinner's Judgment","set":"vow","collector_number":"348","rarity":"mythic","booster":false,"image":"https://cards.scryfall.io/normal/front/2/6/2699d2a8-8f17-42d2-9eb2-8c1ab8dda6c4.jpg?1646449524","uri":"https://scryfall.com/card/vow/348/faithbound-judge-sinners-judgment?utm_source=api","finishes":[{"type":"nonfoil","price":1.4},{"type":"foil","price":1.23}],"showcase":false,"extendedart":true,"inverted":false,"borderless":false,"fullart":false,"etched":false,"promo":false,"promo_types":["boosterfun"]},{"id":"c4c9612e-3acd-4eb7-b34c-c300084625d4","name":"Howling Moon","set":"vow","collector_number":"391","rarity":"rare","booster":false,"image":"https://cards.scryfall.io/normal/front/c/4/c4c9612e-3acd-4eb7-b34c-c300084625d4.jpg?1646615981","uri":"https://scryfall.com/card/vow/391/howling-moon?utm_source=api","finishes":[{"type":"nonfoil","price":1.38},{"type":"foil","price":1.7}],"showcase":false,"extendedart":true,"inverted":false,"borderless":false,"fullart":false,"etched":false,"promo":false,"promo_types":["boosterfun"]},{"id":"52d94eb6-d96c-4b88-9450-b1ee472795fa","name":"Volatile Arsonist // Dire-Strain Anarchist","set":"vow","collector_number":"382","rarity":"mythic","booster":false,"image":"https://cards.scryfall.io/normal/front/5/2/52d94eb6-d96c-4b88-9450-b1ee472795fa.jpg?1646612964","uri":"https://scryfall.com/card/vow/382/volatile-arsonist-dire-strain-anarchist?utm_source=api","finishes":[{"type":"nonfoil","price":1.35},{"type":"foil","price":1.35}],"showcase":false,"extendedart":true,"inverted":false,"borderless":false,"fullart":false,"etched":false,"promo":false,"promo_types":["boosterfun"]},{"id":"4457ff96-a65d-4e9f-bb99-ac5226446263","name":"Henrika Domnathi // Henrika, Infernal Seer","set":"vow","collector_number":"293","rarity":"mythic","booster":false,"image":"https://cards.scryfall.io/normal/front/4/4/4457ff96-a65d-4e9f-bb99-ac5226446263.jpg?1645054759","uri":"https://scryfall.com/card/vow/293/henrika-domnathi-henrika-infernal-seer?utm_source=api","finishes":[{"type":"nonfoil","price":1.27},{"type":"foil","price":2.18}],"showcase":true,"extendedart":false,"inverted":false,"borderless":false,"fullart":false,"etched":false,"promo":false,"promo_types":["boosterfun"]},{"id":"4a1ce3cd-380a-4ecc-b837-7ffeaccd5c91","name":"Ill-Tempered Loner // Howlpack Avenger","set":"vow","collector_number":"378","rarity":"rare","booster":false,"image":"https://cards.scryfall.io/normal/front/4/a/4a1ce3cd-380a-4ecc-b837-7ffeaccd5c91.jpg?1646612900","uri":"https://scryfall.com/card/vow/378/ill-tempered-loner-howlpack-avenger?utm_source=api","finishes":[{"type":"nonfoil","price":1.06},{"type":"foil","price":1}],"showcase":false,"extendedart":true,"inverted":false,"borderless":false,"fullart":false,"etched":false,"promo":false,"promo_types":["boosterfun"]},{"id":"f4135910-57ba-4f1a-ad48-4e14d44bf2a1","name":"Mirrorhall Mimic // Ghastly Mimicry","set":"vow","collector_number":"361","rarity":"rare","booster":false,"image":"https://cards.scryfall.io/normal/front/f/4/f4135910-57ba-4f1a-ad48-4e14d44bf2a1.jpg?1646534546","uri":"https://scryfall.com/card/vow/361/mirrorhall-mimic-ghastly-mimicry?utm_source=api","finishes":[{"type":"nonfoil","price":1.04},{"type":"foil","price":1.29}],"showcase":false,"extendedart":true,"inverted":false,"borderless":false,"fullart":false,"etched":false,"promo":false,"promo_types":["boosterfun"]},{"id":"f3e60e71-bf44-475b-bfce-815ad8abf9e2","name":"Wedding Announcement // Wedding Festivity","set":"vow","collector_number":"355","rarity":"rare","booster":false,"image":"https://cards.scryfall.io/normal/front/f/3/f3e60e71-bf44-475b-bfce-815ad8abf9e2.jpg?1646449769","uri":"https://scryfall.com/card/vow/355/wedding-announcement-wedding-festivity?utm_source=api","finishes":[{"type":"nonfoil","price":1.02},{"type":"foil","price":1.15}],"showcase":false,"extendedart":true,"inverted":false,"borderless":false,"fullart":false,"etched":false,"promo":false,"promo_types":["boosterfun"]},{"id":"87684bef-8ef9-4709-a50e-fa5ff2f67acc","name":"Halana and Alena, Partners","set":"vow","collector_number":"325","rarity":"rare","booster":false,"image":"https://cards.scryfall.io/normal/front/8/7/87684bef-8ef9-4709-a50e-fa5ff2f67acc.jpg?1682717183","uri":"https://scryfall.com/card/vow/325/halana-and-alena-partners?utm_source=api","finishes":[{"type":"nonfoil","price":1},{"type":"foil","price":2.45}],"showcase":true,"extendedart":false,"inverted":true,"borderless":false,"fullart":true,"etched":false,"promo":false,"promo_types":["boosterfun"]},{"id":"8e857c4e-9d85-418a-9200-3bdcceff3f6b","name":"Ulvenwald Oddity // Ulvenwald Behemoth","set":"vow","collector_number":"394","rarity":"rare","booster":false,"image":"https://cards.scryfall.io/normal/front/8/e/8e857c4e-9d85-418a-9200-3bdcceff3f6b.jpg?1646616028","uri":"https://scryfall.com/card/vow/394/ulvenwald-oddity-ulvenwald-behemoth?utm_source=api","finishes":[{"type":"nonfoil","price":0.96},{"type":"foil","price":1.32}],"showcase":false,"extendedart":true,"inverted":false,"borderless":false,"fullart":false,"etched":false,"promo":false,"promo_types":["boosterfun"]},{"id":"48d43ab9-772d-4f4d-8536-3ea60e8f9f82","name":"Falkenrath Forebear","set":"vow","collector_number":"334","rarity":"rare","booster":false,"image":"https://cards.scryfall.io/normal/front/4/8/48d43ab9-772d-4f4d-8536-3ea60e8f9f82.jpg?1645065923","uri":"https://scryfall.com/card/vow/334/falkenrath-forebear?utm_source=api","finishes":[{"type":"nonfoil","price":0.91},{"type":"foil","price":0.89}],"showcase":false,"extendedart":false,"inverted":true,"borderless":true,"fullart":true,"etched":false,"promo":false,"promo_types":["draculaseries","boosterfun"]},{"id":"c1c330f8-7461-48d3-9743-25e66d153538","name":"Cemetery Illuminator","set":"vow","collector_number":"356","rarity":"mythic","booster":false,"image":"https://cards.scryfall.io/normal/front/c/1/c1c330f8-7461-48d3-9743-25e66d153538.jpg?1646534485","uri":"https://scryfall.com/card/vow/356/cemetery-illuminator?utm_source=api","finishes":[{"type":"nonfoil","price":0.88},{"type":"foil","price":1.06}],"showcase":false,"extendedart":true,"inverted":false,"borderless":false,"fullart":false,"etched":false,"promo":false,"promo_types":["boosterfun"]},{"id":"8aa2f823-d66d-42b0-ab3c-180b9a927cb1","name":"Cemetery Protector","set":"vow","collector_number":"347","rarity":"mythic","booster":false,"image":"https://cards.scryfall.io/normal/front/8/a/8aa2f823-d66d-42b0-ab3c-180b9a927cb1.jpg?1646449503","uri":"https://scryfall.com/card/vow/347/cemetery-protector?utm_source=api","finishes":[{"type":"nonfoil","price":0.86},{"type":"foil","price":1.4}],"showcase":false,"extendedart":true,"inverted":false,"borderless":false,"fullart":false,"etched":false,"promo":false,"promo_types":["boosterfun"]},{"id":"c598c30a-056e-44ca-8469-73304763491c","name":"Howlpack Piper // Wildsong Howler","set":"vow","collector_number":"392","rarity":"rare","booster":false,"image":"https://cards.scryfall.io/normal/front/c/5/c598c30a-056e-44ca-8469-73304763491c.jpg?1646615998","uri":"https://scryfall.com/card/vow/392/howlpack-piper-wildsong-howler?utm_source=api","finishes":[{"type":"nonfoil","price":0.85},{"type":"foil","price":1.47}],"showcase":false,"extendedart":true,"inverted":false,"borderless":false,"fullart":false,"etched":false,"promo":false,"promo_types":["boosterfun"]},{"id":"078d0194-0137-45cd-977a-eefae67f9bca","name":"Dig Up","set":"vow","collector_number":"387","rarity":"rare","booster":false,"image":"https://cards.scryfall.io/normal/front/0/7/078d0194-0137-45cd-977a-eefae67f9bca.jpg?1646615939","uri":"https://scryfall.com/card/vow/387/dig-up?utm_source=api","finishes":[{"type":"nonfoil","price":0.82},{"type":"foil","price":0.66}],"showcase":false,"extendedart":true,"inverted":false,"borderless":false,"fullart":false,"etched":false,"promo":false,"promo_types":["boosterfun"]},{"id":"5f8d93bf-8836-469e-a28c-39633959a212","name":"Overcharged Amalgam","set":"vow","collector_number":"363","rarity":"rare","booster":false,"image":"https://cards.scryfall.io/normal/front/5/f/5f8d93bf-8836-469e-a28c-39633959a212.jpg?1646534581","uri":"https://scryfall.com/card/vow/363/overcharged-amalgam?utm_source=api","finishes":[{"type":"nonfoil","price":0.76},{"type":"foil","price":1.12}],"showcase":false,"extendedart":true,"inverted":false,"borderless":false,"fullart":false,"etched":false,"promo":false,"promo_types":["boosterfun"]},{"id":"fc518e53-1fd5-4eeb-a8b7-6db871cc16d6","name":"Consuming Tide","set":"vow","collector_number":"357","rarity":"rare","booster":false,"image":"https://cards.scryfall.io/normal/front/f/c/fc518e53-1fd5-4eeb-a8b7-6db871cc16d6.jpg?1646534495","uri":"https://scryfall.com/card/vow/357/consuming-tide?utm_source=api","finishes":[{"type":"nonfoil","price":0.66},{"type":"foil","price":0.65}],"showcase":false,"extendedart":true,"inverted":false,"borderless":false,"fullart":false,"etched":false,"promo":false,"promo_types":["boosterfun"]},{"id":"c0f0004e-ee4c-4372-be5d-a5102f45210e","name":"Jacob Hauken, Inspector // Hauken's Insight","set":"vow","collector_number":"332","rarity":"mythic","booster":false,"image":"https://cards.scryfall.io/normal/front/c/0/c0f0004e-ee4c-4372-be5d-a5102f45210e.jpg?1644976607","uri":"https://scryfall.com/card/vow/332/jacob-hauken-inspector-haukens-insight?utm_source=api","finishes":[{"type":"nonfoil","price":0.65},{"type":"foil","price":0.83}],"showcase":false,"extendedart":false,"inverted":true,"borderless":true,"fullart":true,"etched":false,"promo":false,"promo_types":["draculaseries","boosterfun"]},{"id":"1830002a-b512-4e51-b3fa-0137d2b4c749","name":"Thalia, Guardian of Thraben","set":"vow","collector_number":"331","rarity":"rare","booster":false,"image":"https://cards.scryfall.io/normal/front/1/8/1830002a-b512-4e51-b3fa-0137d2b4c749.jpg?1644976580","uri":"https://scryfall.com/card/vow/331/thalia-guardian-of-thraben?utm_source=api","finishes":[{"type":"nonfoil","price":0.65},{"type":"foil","price":0.76}],"showcase":false,"extendedart":false,"inverted":true,"borderless":true,"fullart":true,"etched":false,"promo":false,"promo_types":["draculaseries","boosterfun"]},{"id":"169b4aa8-9597-4b57-a957-abee147fdde4","name":"Hopeful Initiate","set":"vow","collector_number":"350","rarity":"rare","booster":false,"image":"https://cards.scryfall.io/normal/front/1/6/169b4aa8-9597-4b57-a957-abee147fdde4.jpg?1646449560","uri":"https://scryfall.com/card/vow/350/hopeful-initiate?utm_source=api","finishes":[{"type":"nonfoil","price":0.64},{"type":"foil","price":0.72}],"showcase":false,"extendedart":true,"inverted":false,"borderless":false,"fullart":false,"etched":false,"promo":false,"promo_types":["boosterfun"]},{"id":"a2437225-d6a9-4cc6-9b3b-148f9300e6b1","name":"Voldaren Estate","set":"vow","collector_number":"397","rarity":"rare","booster":false,"image":"https://cards.scryfall.io/normal/front/a/2/a2437225-d6a9-4cc6-9b3b-148f9300e6b1.jpg?1646616080","uri":"https://scryfall.com/card/vow/397/voldaren-estate?utm_source=api","finishes":[{"type":"nonfoil","price":0.59},{"type":"foil","price":0.92}],"showcase":false,"extendedart":true,"inverted":false,"borderless":false,"fullart":false,"etched":false,"promo":false,"promo_types":["boosterfun"]},{"id":"12c50b51-776c-472b-bda3-f7b82eebe2f4","name":"Runo Stromkirk // Krothuss, Lord of the Deep","set":"vow","collector_number":"316","rarity":"rare","booster":false,"image":"https://cards.scryfall.io/normal/front/1/2/12c50b51-776c-472b-bda3-f7b82eebe2f4.jpg?1645055382","uri":"https://scryfall.com/card/vow/316/runo-stromkirk-krothuss-lord-of-the-deep?utm_source=api","finishes":[{"type":"nonfoil","price":0.58},{"type":"foil","price":1.69}],"showcase":true,"extendedart":false,"inverted":false,"borderless":false,"fullart":false,"etched":false,"promo":false,"promo_types":["boosterfun"]},{"id":"53c5d474-5620-4c5f-95a4-8a128825df83","name":"Geralf, Visionary Stitcher","set":"vow","collector_number":"319","rarity":"rare","booster":false,"image":"https://cards.scryfall.io/normal/front/5/3/53c5d474-5620-4c5f-95a4-8a128825df83.jpg?1682717194","uri":"https://scryfall.com/card/vow/319/geralf-visionary-stitcher?utm_source=api","finishes":[{"type":"nonfoil","price":0.56},{"type":"foil","price":0.66}],"showcase":true,"extendedart":false,"inverted":true,"borderless":false,"fullart":true,"etched":false,"promo":false,"promo_types":["boosterfun"]},{"id":"583344df-41ac-4950-ae63-275df9b0a9e9","name":"Curse of Hospitality","set":"vow","collector_number":"377","rarity":"rare","booster":false,"image":"https://cards.scryfall.io/normal/front/5/8/583344df-41ac-4950-ae63-275df9b0a9e9.jpg?1646612876","uri":"https://scryfall.com/card/vow/377/curse-of-hospitality?utm_source=api","finishes":[{"type":"nonfoil","price":0.54},{"type":"foil","price":0.38}],"showcase":false,"extendedart":true,"inverted":false,"borderless":false,"fullart":false,"etched":false,"promo":false,"promo_types":["boosterfun"]},{"id":"866828f0-71f7-454b-93a7-2f2ea707f53d","name":"Katilda, Dawnhart Martyr // Katilda's Rising Dawn","set":"vow","collector_number":"317","rarity":"rare","booster":false,"image":"https://cards.scryfall.io/normal/front/8/6/866828f0-71f7-454b-93a7-2f2ea707f53d.jpg?1682717174","uri":"https://scryfall.com/card/vow/317/katilda-dawnhart-martyr-katildas-rising-dawn?utm_source=api","finishes":[{"type":"nonfoil","price":0.53},{"type":"foil","price":0.72}],"showcase":true,"extendedart":false,"inverted":true,"borderless":false,"fullart":true,"etched":false,"promo":false,"promo_types":["boosterfun"]},{"id":"061be997-1519-41b6-9933-eb625db88eb2","name":"Path of Peril","set":"vow","collector_number":"373","rarity":"rare","booster":false,"image":"https://cards.scryfall.io/normal/front/0/6/061be997-1519-41b6-9933-eb625db88eb2.jpg?1646536136","uri":"https://scryfall.com/card/vow/373/path-of-peril?utm_source=api","finishes":[{"type":"nonfoil","price":0.52},{"type":"foil","price":0.78}],"showcase":false,"extendedart":true,"inverted":false,"borderless":false,"fullart":false,"etched":false,"promo":false,"promo_types":["boosterfun"]},{"id":"31e09ecd-a8fc-45a6-a997-49b0fc5c88b9","name":"Change of Fortune","set":"vow","collector_number":"375","rarity":"rare","booster":false,"image":"https://cards.scryfall.io/normal/front/3/1/31e09ecd-a8fc-45a6-a997-49b0fc5c88b9.jpg?1646612832","uri":"https://scryfall.com/card/vow/375/change-of-fortune?utm_source=api","finishes":[{"type":"nonfoil","price":0.51},{"type":"foil","price":0.86}],"showcase":false,"extendedart":true,"inverted":false,"borderless":false,"fullart":false,"etched":false,"promo":false,"promo_types":["boosterfun"]},{"id":"15a2d232-484c-4ec2-814b-e1018277a1ff","name":"Savior of Ollenbock","set":"vow","collector_number":"330","rarity":"mythic","booster":false,"image":"https://cards.scryfall.io/normal/front/1/5/15a2d232-484c-4ec2-814b-e1018277a1ff.jpg?1644976562","uri":"https://scryfall.com/card/vow/330/savior-of-ollenbock?utm_source=api","finishes":[{"type":"nonfoil","price":0.5},{"type":"foil","price":0.6}],"showcase":false,"extendedart":false,"inverted":true,"borderless":true,"fullart":true,"etched":false,"promo":false,"promo_types":["draculaseries","boosterfun"]}]}